{
"meta":{"test_sets":[],"test_metrics":[],"learn_metrics":[{"best_value":"Min","name":"RMSE"}],"launch_mode":"Train","parameters":"","iteration_count":1000,"learn_sets":["learn"],"name":"experiment"},
"iterations":[
{"learn":[14.61268541],"iteration":0,"passed_time":0.1436596186,"remaining_time":143.515959},
{"learn":[14.23196558],"iteration":1,"passed_time":0.1461060674,"remaining_time":72.90692763},
{"learn":[13.86674177],"iteration":2,"passed_time":0.1480155337,"remaining_time":49.19049569},
{"learn":[13.49946468],"iteration":3,"passed_time":0.1501587502,"remaining_time":37.3895288},
{"learn":[13.16661202],"iteration":4,"passed_time":0.1522489121,"remaining_time":30.29753351},
{"learn":[12.85632158],"iteration":5,"passed_time":0.1540985218,"remaining_time":25.52898844},
{"learn":[12.56784336],"iteration":6,"passed_time":0.1560603415,"remaining_time":22.13827416},
{"learn":[12.31617801],"iteration":7,"passed_time":0.1582529897,"remaining_time":19.62337072},
{"learn":[12.01509946],"iteration":8,"passed_time":0.159734544,"remaining_time":17.58854812},
{"learn":[11.71512571],"iteration":9,"passed_time":0.1610197295,"remaining_time":15.94095322},
{"learn":[11.43264457],"iteration":10,"passed_time":0.1625567851,"remaining_time":14.61533277},
{"learn":[11.17973129],"iteration":11,"passed_time":0.1638443508,"remaining_time":13.48985155},
{"learn":[10.93746433],"iteration":12,"passed_time":0.1650785887,"remaining_time":12.53327439},
{"learn":[10.69387075],"iteration":13,"passed_time":0.1662484432,"remaining_time":11.70864036},
{"learn":[10.4615922],"iteration":14,"passed_time":0.1673615242,"remaining_time":10.99007342},
{"learn":[10.2299235],"iteration":15,"passed_time":0.168558727,"remaining_time":10.36636171},
{"learn":[10.01419731],"iteration":16,"passed_time":0.1696025413,"remaining_time":9.807017537},
{"learn":[9.795856918],"iteration":17,"passed_time":0.1710584389,"remaining_time":9.332188169},
{"learn":[9.60040151],"iteration":18,"passed_time":0.1722697468,"remaining_time":8.894559034},
{"learn":[9.418664989],"iteration":19,"passed_time":0.1733818685,"remaining_time":8.495711557},
{"learn":[9.249278645],"iteration":20,"passed_time":0.1743779596,"remaining_time":8.129334404},
{"learn":[9.090113396],"iteration":21,"passed_time":0.1752828655,"remaining_time":7.792120113},
{"learn":[8.909548708],"iteration":22,"passed_time":0.1762054036,"remaining_time":7.4848991},
{"learn":[8.740140208],"iteration":23,"passed_time":0.1772314066,"remaining_time":7.207410536},
{"learn":[8.59377682],"iteration":24,"passed_time":0.1782983653,"remaining_time":6.953636248},
{"learn":[8.453885414],"iteration":25,"passed_time":0.1791141989,"remaining_time":6.70989345},
{"learn":[8.317732234],"iteration":26,"passed_time":0.1801527028,"remaining_time":6.492169622},
{"learn":[8.180896085],"iteration":27,"passed_time":0.1809688575,"remaining_time":6.282204624},
{"learn":[8.053220863],"iteration":28,"passed_time":0.1818968186,"remaining_time":6.090407272},
{"learn":[7.924234474],"iteration":29,"passed_time":0.1827227685,"remaining_time":5.908036183},
{"learn":[7.818879511],"iteration":30,"passed_time":0.1835156998,"remaining_time":5.736345585},
{"learn":[7.719346395],"iteration":31,"passed_time":0.1843655786,"remaining_time":5.577058752},
{"learn":[7.624163594],"iteration":32,"passed_time":0.1852259453,"remaining_time":5.427681489},
{"learn":[7.524952543],"iteration":33,"passed_time":0.1862446335,"remaining_time":5.291538705},
{"learn":[7.424464745],"iteration":34,"passed_time":0.1870334407,"remaining_time":5.156779152},
{"learn":[7.327482321],"iteration":35,"passed_time":0.1877192916,"remaining_time":5.026705476},
{"learn":[7.238666841],"iteration":36,"passed_time":0.1883490577,"remaining_time":4.902166016},
{"learn":[7.158842395],"iteration":37,"passed_time":0.1890065076,"remaining_time":4.784848957},
{"learn":[7.074348246],"iteration":38,"passed_time":0.1896227345,"remaining_time":4.672498663},
{"learn":[6.992269093],"iteration":39,"passed_time":0.1902677861,"remaining_time":4.566426867},
{"learn":[6.925219745],"iteration":40,"passed_time":0.1909631254,"remaining_time":4.466674079},
{"learn":[6.86013671],"iteration":41,"passed_time":0.1916047886,"remaining_time":4.370413988},
{"learn":[6.786739622],"iteration":42,"passed_time":0.1922293931,"remaining_time":4.278221609},
{"learn":[6.73057926],"iteration":43,"passed_time":0.192862667,"remaining_time":4.190379764},
{"learn":[6.666356486],"iteration":44,"passed_time":0.1936488719,"remaining_time":4.109659393},
{"learn":[6.606182832],"iteration":45,"passed_time":0.1944217613,"remaining_time":4.032138268},
{"learn":[6.547854615],"iteration":46,"passed_time":0.1952872409,"remaining_time":3.959760439},
{"learn":[6.49240675],"iteration":47,"passed_time":0.1961030013,"remaining_time":3.889376193},
{"learn":[6.431317261],"iteration":48,"passed_time":0.1968183404,"remaining_time":3.819882484},
{"learn":[6.377586395],"iteration":49,"passed_time":0.1975925238,"remaining_time":3.754257951},
{"learn":[6.327558015],"iteration":50,"passed_time":0.1983087465,"remaining_time":3.690098048},
{"learn":[6.282040317],"iteration":51,"passed_time":0.1990024882,"remaining_time":3.627968439},
{"learn":[6.237655841],"iteration":52,"passed_time":0.1998382417,"remaining_time":3.570694621},
{"learn":[6.192792003],"iteration":53,"passed_time":0.2008488508,"remaining_time":3.518574312},
{"learn":[6.150579347],"iteration":54,"passed_time":0.2017348103,"remaining_time":3.466170832},
{"learn":[6.115693845],"iteration":55,"passed_time":0.2025310047,"remaining_time":3.414094079},
{"learn":[6.078780782],"iteration":56,"passed_time":0.2032579727,"remaining_time":3.362671373},
{"learn":[6.045146957],"iteration":57,"passed_time":0.2040346364,"remaining_time":3.313803922},
{"learn":[6.008080327],"iteration":58,"passed_time":0.2047862698,"remaining_time":3.266167456},
{"learn":[5.977575734],"iteration":59,"passed_time":0.205460665,"remaining_time":3.218883751},
{"learn":[5.948036502],"iteration":60,"passed_time":0.2061752465,"remaining_time":3.173746827},
{"learn":[5.914888282],"iteration":61,"passed_time":0.2068715711,"remaining_time":3.129766673},
{"learn":[5.884957796],"iteration":62,"passed_time":0.2075890685,"remaining_time":3.087475511},
{"learn":[5.849539885],"iteration":63,"passed_time":0.2084157339,"remaining_time":3.048080109},
{"learn":[5.821387627],"iteration":64,"passed_time":0.2092206759,"remaining_time":3.009558953},
{"learn":[5.797012279],"iteration":65,"passed_time":0.2099041692,"remaining_time":2.970462031},
{"learn":[5.768685095],"iteration":66,"passed_time":0.2105691333,"remaining_time":2.932253751},
{"learn":[5.755484587],"iteration":67,"passed_time":0.2109386768,"remaining_time":2.891100689},
{"learn":[5.731887055],"iteration":68,"passed_time":0.2117059447,"remaining_time":2.856496153},
{"learn":[5.707148487],"iteration":69,"passed_time":0.2125803779,"remaining_time":2.824282163},
{"learn":[5.685365039],"iteration":70,"passed_time":0.2134037062,"remaining_time":2.792282297},
{"learn":[5.663541834],"iteration":71,"passed_time":0.2142215946,"remaining_time":2.761078331},
{"learn":[5.638108797],"iteration":72,"passed_time":0.215210159,"remaining_time":2.732874211},
{"learn":[5.619204893],"iteration":73,"passed_time":0.2160886978,"remaining_time":2.70402884},
{"learn":[5.598472793],"iteration":74,"passed_time":0.2169439761,"remaining_time":2.675642372},
{"learn":[5.577007075],"iteration":75,"passed_time":0.2176115625,"remaining_time":2.645698471},
{"learn":[5.562637084],"iteration":76,"passed_time":0.2183287312,"remaining_time":2.617109336},
{"learn":[5.54729991],"iteration":77,"passed_time":0.218991024,"remaining_time":2.588586207},
{"learn":[5.530737623],"iteration":78,"passed_time":0.2196830354,"remaining_time":2.561114881},
{"learn":[5.513704873],"iteration":79,"passed_time":0.2203869338,"remaining_time":2.534449739},
{"learn":[5.501575529],"iteration":80,"passed_time":0.2211186153,"remaining_time":2.508740833},
{"learn":[5.484080734],"iteration":81,"passed_time":0.2218913593,"remaining_time":2.484100827},
{"learn":[5.472178894],"iteration":82,"passed_time":0.2227916324,"remaining_time":2.461444903},
{"learn":[5.458923342],"iteration":83,"passed_time":0.223534039,"remaining_time":2.437585473},
{"learn":[5.451382371],"iteration":84,"passed_time":0.2240511789,"remaining_time":2.411845043},
{"learn":[5.441410748],"iteration":85,"passed_time":0.2247861823,"remaining_time":2.389006635},
{"learn":[5.434047468],"iteration":86,"passed_time":0.2252451791,"remaining_time":2.363779868},
{"learn":[5.422107497],"iteration":87,"passed_time":0.2260620166,"remaining_time":2.342824535},
{"learn":[5.40731265],"iteration":88,"passed_time":0.2268342064,"remaining_time":2.321864742},
{"learn":[5.396360181],"iteration":89,"passed_time":0.2275641214,"remaining_time":2.300926116},
{"learn":[5.383793239],"iteration":90,"passed_time":0.2282861498,"remaining_time":2.280352859},
{"learn":[5.369605034],"iteration":91,"passed_time":0.2292197249,"remaining_time":2.262299024},
{"learn":[5.357467333],"iteration":92,"passed_time":0.2301124831,"remaining_time":2.244215292},
{"learn":[5.341109968],"iteration":93,"passed_time":0.2309047173,"remaining_time":2.225528446},
{"learn":[5.330529276],"iteration":94,"passed_time":0.2316397754,"remaining_time":2.20667365},
{"learn":[5.319862075],"iteration":95,"passed_time":0.2323074712,"remaining_time":2.18756202},
{"learn":[5.313052243],"iteration":96,"passed_time":0.2329568731,"remaining_time":2.168660375},
{"learn":[5.299677207],"iteration":97,"passed_time":0.2336226703,"remaining_time":2.150282129},
{"learn":[5.287546698],"iteration":98,"passed_time":0.2343261829,"remaining_time":2.132604957},
{"learn":[5.279803754],"iteration":99,"passed_time":0.2350220661,"remaining_time":2.115198595},
{"learn":[5.272254612],"iteration":100,"passed_time":0.2357911299,"remaining_time":2.098774512},
{"learn":[5.268813888],"iteration":101,"passed_time":0.2363410799,"remaining_time":2.080728331},
{"learn":[5.258113767],"iteration":102,"passed_time":0.2370764104,"remaining_time":2.064636312},
{"learn":[5.251018576],"iteration":103,"passed_time":0.2377994923,"remaining_time":2.048734087},
{"learn":[5.24171237],"iteration":104,"passed_time":0.2384763568,"remaining_time":2.032727042},
{"learn":[5.233984943],"iteration":105,"passed_time":0.2391546373,"remaining_time":2.017021186},
{"learn":[5.226240449],"iteration":106,"passed_time":0.2398658994,"remaining_time":2.001871478},
{"learn":[5.220541644],"iteration":107,"passed_time":0.240660735,"remaining_time":1.987679404},
{"learn":[5.211712096],"iteration":108,"passed_time":0.2413991807,"remaining_time":1.973272202},
{"learn":[5.203388597],"iteration":109,"passed_time":0.24207141,"remaining_time":1.958577772},
{"learn":[5.196026544],"iteration":110,"passed_time":0.242998395,"remaining_time":1.946176335},
{"learn":[5.188716772],"iteration":111,"passed_time":0.2439084456,"remaining_time":1.933845533},
{"learn":[5.182163132],"iteration":112,"passed_time":0.2450698006,"remaining_time":1.923689497},
{"learn":[5.17764747],"iteration":113,"passed_time":0.2458321919,"remaining_time":1.910590544},
{"learn":[5.170548056],"iteration":114,"passed_time":0.2465925182,"remaining_time":1.897690249},
{"learn":[5.165901827],"iteration":115,"passed_time":0.247237458,"remaining_time":1.884119939},
{"learn":[5.160333668],"iteration":116,"passed_time":0.2479981114,"remaining_time":1.871643866},
{"learn":[5.148953243],"iteration":117,"passed_time":0.248801439,"remaining_time":1.859685333},
{"learn":[5.144729126],"iteration":118,"passed_time":0.2493458339,"remaining_time":1.845997308},
{"learn":[5.139939946],"iteration":119,"passed_time":0.2501667585,"remaining_time":1.834556229},
{"learn":[5.132898872],"iteration":120,"passed_time":0.2510250224,"remaining_time":1.82356194},
{"learn":[5.129073077],"iteration":121,"passed_time":0.2517363812,"remaining_time":1.811676579},
{"learn":[5.127123916],"iteration":122,"passed_time":0.2521940041,"remaining_time":1.798163753},
{"learn":[5.121282057],"iteration":123,"passed_time":0.2529799611,"remaining_time":1.787181015},
{"learn":[5.114489821],"iteration":124,"passed_time":0.2537340941,"remaining_time":1.776138659},
{"learn":[5.107777291],"iteration":125,"passed_time":0.2544433863,"remaining_time":1.764948568},
{"learn":[5.103518754],"iteration":126,"passed_time":0.2552125955,"remaining_time":1.754335401},
{"learn":[5.101133351],"iteration":127,"passed_time":0.2556844614,"remaining_time":1.741850394},
{"learn":[5.096462705],"iteration":128,"passed_time":0.2563523363,"remaining_time":1.730875077},
{"learn":[5.08562082],"iteration":129,"passed_time":0.2571053511,"remaining_time":1.720628119},
{"learn":[5.080483682],"iteration":130,"passed_time":0.2578030345,"remaining_time":1.710159061},
{"learn":[5.07437499],"iteration":131,"passed_time":0.2586667745,"remaining_time":1.700930002},
{"learn":[5.070683732],"iteration":132,"passed_time":0.2594069841,"remaining_time":1.691021468},
{"learn":[5.06432037],"iteration":133,"passed_time":0.2602861383,"remaining_time":1.682147729},
{"learn":[5.057436484],"iteration":134,"passed_time":0.260967565,"remaining_time":1.672125509},
{"learn":[5.053254656],"iteration":135,"passed_time":0.2616428295,"remaining_time":1.662201505},
{"learn":[5.04801663],"iteration":136,"passed_time":0.2623297919,"remaining_time":1.652486208},
{"learn":[5.045680836],"iteration":137,"passed_time":0.2628914457,"remaining_time":1.642119031},
{"learn":[5.041857933],"iteration":138,"passed_time":0.2637081343,"remaining_time":1.633472688},
{"learn":[5.035264888],"iteration":139,"passed_time":0.2644375886,"remaining_time":1.62440233},
{"learn":[5.028771948],"iteration":140,"passed_time":0.2652333886,"remaining_time":1.615854474},
{"learn":[5.024912247],"iteration":141,"passed_time":0.2659718351,"remaining_time":1.607069257},
{"learn":[5.02239068],"iteration":142,"passed_time":0.2667359853,"remaining_time":1.598550625},
{"learn":[5.017110572],"iteration":143,"passed_time":0.2674762269,"remaining_time":1.589997571},
{"learn":[5.010707886],"iteration":144,"passed_time":0.2681860781,"remaining_time":1.581373081},
{"learn":[5.004389868],"iteration":145,"passed_time":0.2688211614,"remaining_time":1.57241967},
{"learn":[4.997628683],"iteration":146,"passed_time":0.2695218152,"remaining_time":1.563959921},
{"learn":[4.991497851],"iteration":147,"passed_time":0.2702239901,"remaining_time":1.555613781},
{"learn":[4.988345253],"iteration":148,"passed_time":0.270921966,"remaining_time":1.547346262},
{"learn":[4.98460423],"iteration":149,"passed_time":0.2716165721,"remaining_time":1.539160575},
{"learn":[4.982441783],"iteration":150,"passed_time":0.2723417383,"remaining_time":1.531245932},
{"learn":[4.977461771],"iteration":151,"passed_time":0.2730781484,"remaining_time":1.523488617},
{"learn":[4.973601586],"iteration":152,"passed_time":0.2738242124,"remaining_time":1.515876522},
{"learn":[4.968328804],"iteration":153,"passed_time":0.2745641832,"remaining_time":1.508320123},
{"learn":[4.9640736],"iteration":154,"passed_time":0.2754142772,"remaining_time":1.501452027},
{"learn":[4.960865882],"iteration":155,"passed_time":0.2761808464,"remaining_time":1.494209195},
{"learn":[4.957014156],"iteration":156,"passed_time":0.2769673145,"remaining_time":1.487155708},
{"learn":[4.952244852],"iteration":157,"passed_time":0.2778691448,"remaining_time":1.480796329},
{"learn":[4.949695675],"iteration":158,"passed_time":0.2785414271,"remaining_time":1.473291448},
{"learn":[4.946584698],"iteration":159,"passed_time":0.2793064004,"remaining_time":1.466358602},
{"learn":[4.940192834],"iteration":160,"passed_time":0.2800016085,"remaining_time":1.459138817},
{"learn":[4.936727994],"iteration":161,"passed_time":0.2807500595,"remaining_time":1.452274999},
{"learn":[4.932342063],"iteration":162,"passed_time":0.2814598031,"remaining_time":1.445287455},
{"learn":[4.925830838],"iteration":163,"passed_time":0.2821743762,"remaining_time":1.438401089},
{"learn":[4.922571773],"iteration":164,"passed_time":0.2828892495,"remaining_time":1.431591051},
{"learn":[4.918395814],"iteration":165,"passed_time":0.2835771612,"remaining_time":1.424718991},
{"learn":[4.911142452],"iteration":166,"passed_time":0.2842515202,"remaining_time":1.417853391},
{"learn":[4.908276131],"iteration":167,"passed_time":0.2848976498,"remaining_time":1.410921694},
{"learn":[4.904584645],"iteration":168,"passed_time":0.2856038654,"remaining_time":1.404359835},
{"learn":[4.89795517],"iteration":169,"passed_time":0.2863052852,"remaining_time":1.397843451},
{"learn":[4.895556491],"iteration":170,"passed_time":0.2869914287,"remaining_time":1.39132102},
{"learn":[4.890591233],"iteration":171,"passed_time":0.2877321042,"remaining_time":1.385128967},
{"learn":[4.884629277],"iteration":172,"passed_time":0.2884052238,"remaining_time":1.378676995},
{"learn":[4.880550786],"iteration":173,"passed_time":0.2892109065,"remaining_time":1.37292074},
{"learn":[4.876384842],"iteration":174,"passed_time":0.2899456645,"remaining_time":1.366886704},
{"learn":[4.872638238],"iteration":175,"passed_time":0.2906924617,"remaining_time":1.360969252},
{"learn":[4.869137118],"iteration":176,"passed_time":0.2914047058,"remaining_time":1.354949564},
{"learn":[4.863587157],"iteration":177,"passed_time":0.292092314,"remaining_time":1.348875742},
{"learn":[4.858028614],"iteration":178,"passed_time":0.2928199025,"remaining_time":1.343045474},
{"learn":[4.853838176],"iteration":179,"passed_time":0.2935885324,"remaining_time":1.33745887},
{"learn":[4.853462329],"iteration":180,"passed_time":0.2939468717,"remaining_time":1.330068994},
{"learn":[4.851573196],"iteration":181,"passed_time":0.2946547983,"remaining_time":1.32432761},
{"learn":[4.848442087],"iteration":182,"passed_time":0.2952926772,"remaining_time":1.31832851},
{"learn":[4.845547104],"iteration":183,"passed_time":0.2959971995,"remaining_time":1.312683233},
{"learn":[4.839868817],"iteration":184,"passed_time":0.2967187041,"remaining_time":1.307166183},
{"learn":[4.836336958],"iteration":185,"passed_time":0.2974854557,"remaining_time":1.301898715},
{"learn":[4.831124789],"iteration":186,"passed_time":0.2981401075,"remaining_time":1.296192018},
{"learn":[4.827407333],"iteration":187,"passed_time":0.2988923219,"remaining_time":1.290960454},
{"learn":[4.824088918],"iteration":188,"passed_time":0.2995832688,"remaining_time":1.285513392},
{"learn":[4.820934539],"iteration":189,"passed_time":0.3002749918,"remaining_time":1.280119702},
{"learn":[4.816975227],"iteration":190,"passed_time":0.300903849,"remaining_time":1.274508973},
{"learn":[4.812340486],"iteration":191,"passed_time":0.3015538479,"remaining_time":1.26903911},
{"learn":[4.806402747],"iteration":192,"passed_time":0.3022650217,"remaining_time":1.263874987},
{"learn":[4.801521788],"iteration":193,"passed_time":0.302951261,"remaining_time":1.258653177},
{"learn":[4.797601172],"iteration":194,"passed_time":0.3038091348,"remaining_time":1.254186428},
{"learn":[4.792694629],"iteration":195,"passed_time":0.3045091068,"remaining_time":1.249108785},
{"learn":[4.789794613],"iteration":196,"passed_time":0.3052978796,"remaining_time":1.24443755},
{"learn":[4.785367055],"iteration":197,"passed_time":0.3060922721,"remaining_time":1.239828294},
{"learn":[4.780376856],"iteration":198,"passed_time":0.3068228816,"remaining_time":1.235000644},
{"learn":[4.776691261],"iteration":199,"passed_time":0.3075094539,"remaining_time":1.230037816},
{"learn":[4.773470753],"iteration":200,"passed_time":0.3081511836,"remaining_time":1.224939282},
{"learn":[4.77207327],"iteration":201,"passed_time":0.3088322118,"remaining_time":1.220040124},
{"learn":[4.767347177],"iteration":202,"passed_time":0.3094886712,"remaining_time":1.215086064},
{"learn":[4.763983068],"iteration":203,"passed_time":0.3101388332,"remaining_time":1.210149565},
{"learn":[4.761588849],"iteration":204,"passed_time":0.3108025385,"remaining_time":1.205307406},
{"learn":[4.758558086],"iteration":205,"passed_time":0.3115367449,"remaining_time":1.200777551},
{"learn":[4.753678804],"iteration":206,"passed_time":0.3122563359,"remaining_time":1.196228378},
{"learn":[4.746510889],"iteration":207,"passed_time":0.3129281246,"remaining_time":1.191534013},
{"learn":[4.744840601],"iteration":208,"passed_time":0.3136639747,"remaining_time":1.187120593},
{"learn":[4.741702222],"iteration":209,"passed_time":0.314327337,"remaining_time":1.182469506},
{"learn":[4.739352853],"iteration":210,"passed_time":0.3149895155,"remaining_time":1.17785179},
{"learn":[4.735539287],"iteration":211,"passed_time":0.3157212407,"remaining_time":1.173529895},
{"learn":[4.730726751],"iteration":212,"passed_time":0.3164168389,"remaining_time":1.169108226},
{"learn":[4.726416092],"iteration":213,"passed_time":0.3171123867,"remaining_time":1.164721196},
{"learn":[4.721293082],"iteration":214,"passed_time":0.3178021565,"remaining_time":1.160347409},
{"learn":[4.718443695],"iteration":215,"passed_time":0.3186605718,"remaining_time":1.156619853},
{"learn":[4.711627962],"iteration":216,"passed_time":0.319395677,"remaining_time":1.152473802},
{"learn":[4.709790764],"iteration":217,"passed_time":0.3201336627,"remaining_time":1.148369377},
{"learn":[4.706913073],"iteration":218,"passed_time":0.3208155434,"remaining_time":1.144095614},
{"learn":[4.703846389],"iteration":219,"passed_time":0.3214916849,"remaining_time":1.139834156},
{"learn":[4.701001135],"iteration":220,"passed_time":0.3221344151,"remaining_time":1.135487373},
{"learn":[4.700380864],"iteration":221,"passed_time":0.3228783688,"remaining_time":1.131528698},
{"learn":[4.695837486],"iteration":222,"passed_time":0.3236404658,"remaining_time":1.127662071},
{"learn":[4.691242996],"iteration":223,"passed_time":0.3244152083,"remaining_time":1.123866972},
{"learn":[4.690284609],"iteration":224,"passed_time":0.3251050008,"remaining_time":1.119806114},
{"learn":[4.68827119],"iteration":225,"passed_time":0.325877643,"remaining_time":1.116058831},
{"learn":[4.686922425],"iteration":226,"passed_time":0.3265782624,"remaining_time":1.112092497},
{"learn":[4.686085874],"iteration":227,"passed_time":0.3273407815,"remaining_time":1.108364401},
{"learn":[4.683230741],"iteration":228,"passed_time":0.3280753704,"remaining_time":1.104568169},
{"learn":[4.6773487],"iteration":229,"passed_time":0.3287356984,"remaining_time":1.100549947},
{"learn":[4.671462906],"iteration":230,"passed_time":0.3295258424,"remaining_time":1.096992956},
{"learn":[4.664799601],"iteration":231,"passed_time":0.3302681624,"remaining_time":1.093301503},
{"learn":[4.660979386],"iteration":232,"passed_time":0.3309096365,"remaining_time":1.089303396},
{"learn":[4.656281279],"iteration":233,"passed_time":0.3316531143,"remaining_time":1.085667887},
{"learn":[4.651997094],"iteration":234,"passed_time":0.3324109107,"remaining_time":1.082103603},
{"learn":[4.650151977],"iteration":235,"passed_time":0.3331403767,"remaining_time":1.078471389},
{"learn":[4.648478046],"iteration":236,"passed_time":0.3337787583,"remaining_time":1.074570433},
{"learn":[4.646364602],"iteration":237,"passed_time":0.3344948852,"remaining_time":1.070945809},
{"learn":[4.642635873],"iteration":238,"passed_time":0.3352885547,"remaining_time":1.067592427},
{"learn":[4.640860821],"iteration":239,"passed_time":0.3359512478,"remaining_time":1.063845618},
{"learn":[4.639446822],"iteration":240,"passed_time":0.3366649919,"remaining_time":1.060285182},
{"learn":[4.637120072],"iteration":241,"passed_time":0.3373548819,"remaining_time":1.056673556},
{"learn":[4.633769267],"iteration":242,"passed_time":0.3381131643,"remaining_time":1.053299034},
{"learn":[4.630491517],"iteration":243,"passed_time":0.338758638,"remaining_time":1.049596436},
{"learn":[4.627813333],"iteration":244,"passed_time":0.339524052,"remaining_time":1.046288405},
{"learn":[4.622496304],"iteration":245,"passed_time":0.3402817474,"remaining_time":1.042977389},
{"learn":[4.618979301],"iteration":246,"passed_time":0.3410554095,"remaining_time":1.039735722},
{"learn":[4.616563458],"iteration":247,"passed_time":0.3418004167,"remaining_time":1.03642707},
{"learn":[4.614759385],"iteration":248,"passed_time":0.3425330382,"remaining_time":1.033101653},
{"learn":[4.61251363],"iteration":249,"passed_time":0.3432179583,"remaining_time":1.029653875},
{"learn":[4.608796693],"iteration":250,"passed_time":0.3439329098,"remaining_time":1.026317727},
{"learn":[4.60847774],"iteration":251,"passed_time":0.3445193896,"remaining_time":1.022621045},
{"learn":[4.605195659],"iteration":252,"passed_time":0.3451252184,"remaining_time":1.01900608},
{"learn":[4.60103766],"iteration":253,"passed_time":0.3457229706,"remaining_time":1.015391087},
{"learn":[4.599325598],"iteration":254,"passed_time":0.346330629,"remaining_time":1.0118287},
{"learn":[4.597012808],"iteration":255,"passed_time":0.3470745431,"remaining_time":1.008685391},
{"learn":[4.594161533],"iteration":256,"passed_time":0.347684549,"remaining_time":1.005173618},
{"learn":[4.592197259],"iteration":257,"passed_time":0.3483418593,"remaining_time":1.001820386},
{"learn":[4.58952828],"iteration":258,"passed_time":0.3489311094,"remaining_time":0.9982932514},
{"learn":[4.585816572],"iteration":259,"passed_time":0.3495181996,"remaining_time":0.9947825681},
{"learn":[4.582934052],"iteration":260,"passed_time":0.3501044448,"remaining_time":0.9912918954},
{"learn":[4.582234842],"iteration":261,"passed_time":0.3506683914,"remaining_time":0.9877605834},
{"learn":[4.57571562],"iteration":262,"passed_time":0.3512874416,"remaining_time":0.9844062527},
{"learn":[4.571197349],"iteration":263,"passed_time":0.3518708617,"remaining_time":0.9809733115},
{"learn":[4.56723703],"iteration":264,"passed_time":0.3524728801,"remaining_time":0.9776134599},
{"learn":[4.560335567],"iteration":265,"passed_time":0.3531131939,"remaining_time":0.9743800162},
{"learn":[4.554709345],"iteration":266,"passed_time":0.3537269514,"remaining_time":0.9710930912},
{"learn":[4.552806306],"iteration":267,"passed_time":0.3543660553,"remaining_time":0.967895345},
{"learn":[4.550766241],"iteration":268,"passed_time":0.3549498058,"remaining_time":0.9645662009},
{"learn":[4.549216045],"iteration":269,"passed_time":0.3555441259,"remaining_time":0.9612859701},
{"learn":[4.547687452],"iteration":270,"passed_time":0.3561388815,"remaining_time":0.958026733},
{"learn":[4.545642435],"iteration":271,"passed_time":0.3567262525,"remaining_time":0.954767323},
{"learn":[4.543930359],"iteration":272,"passed_time":0.3574460554,"remaining_time":0.9518801547},
{"learn":[4.541029943],"iteration":273,"passed_time":0.358191271,"remaining_time":0.9490761415},
{"learn":[4.537781449],"iteration":274,"passed_time":0.3589588643,"remaining_time":0.9463460968},
{"learn":[4.53066128],"iteration":275,"passed_time":0.3595679814,"remaining_time":0.94321456},
{"learn":[4.526763956],"iteration":276,"passed_time":0.3601453369,"remaining_time":0.9400183343},
{"learn":[4.522036004],"iteration":277,"passed_time":0.3608530669,"remaining_time":0.9371795478},
{"learn":[4.515307629],"iteration":278,"passed_time":0.3614810623,"remaining_time":0.9341499853},
{"learn":[4.51109143],"iteration":279,"passed_time":0.3621258356,"remaining_time":0.9311807201},
{"learn":[4.508233494],"iteration":280,"passed_time":0.3628234693,"remaining_time":0.9283632543},
{"learn":[4.502555629],"iteration":281,"passed_time":0.3634565801,"remaining_time":0.9253965408},
{"learn":[4.500081355],"iteration":282,"passed_time":0.3641230962,"remaining_time":0.922530954},
{"learn":[4.495281743],"iteration":283,"passed_time":0.3647422869,"remaining_time":0.9195615401},
{"learn":[4.492138869],"iteration":284,"passed_time":0.3653776341,"remaining_time":0.9166491522},
{"learn":[4.491708261],"iteration":285,"passed_time":0.3659572606,"remaining_time":0.9136135806},
{"learn":[4.489398865],"iteration":286,"passed_time":0.3665780243,"remaining_time":0.9106973218},
{"learn":[4.485796373],"iteration":287,"passed_time":0.3672032149,"remaining_time":0.9078079479},
{"learn":[4.479542205],"iteration":288,"passed_time":0.3678040343,"remaining_time":0.904874285},
{"learn":[4.475986993],"iteration":289,"passed_time":0.368382582,"remaining_time":0.9019021836},
{"learn":[4.468661855],"iteration":290,"passed_time":0.3689804797,"remaining_time":0.8989936773},
{"learn":[4.463785664],"iteration":291,"passed_time":0.3696237068,"remaining_time":0.8962109055},
{"learn":[4.460445831],"iteration":292,"passed_time":0.3702210083,"remaining_time":0.8933319212},
{"learn":[4.45692492],"iteration":293,"passed_time":0.3708066902,"remaining_time":0.8904405554},
{"learn":[4.454031688],"iteration":294,"passed_time":0.3715173982,"remaining_time":0.8878636126},
{"learn":[4.451672391],"iteration":295,"passed_time":0.3722638095,"remaining_time":0.8853841955},
{"learn":[4.45031553],"iteration":296,"passed_time":0.3730574394,"remaining_time":0.8830282152},
{"learn":[4.446782666],"iteration":297,"passed_time":0.3736712944,"remaining_time":0.8802592238},
{"learn":[4.444369689],"iteration":298,"passed_time":0.3743566939,"remaining_time":0.8776723826},
{"learn":[4.44411683],"iteration":299,"passed_time":0.375048411,"remaining_time":0.8751129589},
{"learn":[4.440876943],"iteration":300,"passed_time":0.3758684358,"remaining_time":0.8728639091},
{"learn":[4.439336453],"iteration":301,"passed_time":0.3767621441,"remaining_time":0.8707946244},
{"learn":[4.436666901],"iteration":302,"passed_time":0.3776014339,"remaining_time":0.868607919},
{"learn":[4.433043336],"iteration":303,"passed_time":0.3784792832,"remaining_time":0.866518359},
{"learn":[4.431419305],"iteration":304,"passed_time":0.3793995604,"remaining_time":0.8645334246},
{"learn":[4.428859646],"iteration":305,"passed_time":0.3801367987,"remaining_time":0.8621403212},
{"learn":[4.424552441],"iteration":306,"passed_time":0.3807707216,"remaining_time":0.8595247886},
{"learn":[4.422706391],"iteration":307,"passed_time":0.3813540947,"remaining_time":0.8568085503},
{"learn":[4.421427994],"iteration":308,"passed_time":0.3819245742,"remaining_time":0.854077284},
{"learn":[4.418733158],"iteration":309,"passed_time":0.3825385469,"remaining_time":0.8514567657},
{"learn":[4.415656941],"iteration":310,"passed_time":0.3831544686,"remaining_time":0.8488534689},
{"learn":[4.410747417],"iteration":311,"passed_time":0.3837722004,"remaining_time":0.8462669035},
{"learn":[4.408126521],"iteration":312,"passed_time":0.3843884408,"remaining_time":0.8436896447},
{"learn":[4.407843853],"iteration":313,"passed_time":0.3849616117,"remaining_time":0.8410307822},
{"learn":[4.405219398],"iteration":314,"passed_time":0.3856799187,"remaining_time":0.8387007756},
{"learn":[4.402708465],"iteration":315,"passed_time":0.3863791457,"remaining_time":0.8363396699},
{"learn":[4.40104971],"iteration":316,"passed_time":0.3869731287,"remaining_time":0.8337622931},
{"learn":[4.400830038],"iteration":317,"passed_time":0.3875341662,"remaining_time":0.8311267337},
{"learn":[4.39784288],"iteration":318,"passed_time":0.388237228,"remaining_time":0.828807374},
{"learn":[4.393741845],"iteration":319,"passed_time":0.3888581406,"remaining_time":0.8263235488},
{"learn":[4.393425936],"iteration":320,"passed_time":0.3894286176,"remaining_time":0.823744646},
{"learn":[4.390505974],"iteration":321,"passed_time":0.3900323571,"remaining_time":0.821248255},
{"learn":[4.390305136],"iteration":322,"passed_time":0.3906061519,"remaining_time":0.8187008199},
{"learn":[4.38568203],"iteration":323,"passed_time":0.3912326549,"remaining_time":0.8162755391},
{"learn":[4.383057135],"iteration":324,"passed_time":0.391817284,"remaining_time":0.8137743591},
{"learn":[4.380662684],"iteration":325,"passed_time":0.3925615715,"remaining_time":0.8116150281},
{"learn":[4.37805727],"iteration":326,"passed_time":0.3934677167,"remaining_time":0.8097974719},
{"learn":[4.373708319],"iteration":327,"passed_time":0.3940916948,"remaining_time":0.8074073746},
{"learn":[4.36887921],"iteration":328,"passed_time":0.3946919508,"remaining_time":0.8049796323},
{"learn":[4.367895929],"iteration":329,"passed_time":0.3952691172,"remaining_time":0.8025160864},
{"learn":[4.362140573],"iteration":330,"passed_time":0.3959082631,"remaining_time":0.8001892085},
{"learn":[4.361931924],"iteration":331,"passed_time":0.396485685,"remaining_time":0.797748306},
{"learn":[4.359656377],"iteration":332,"passed_time":0.3970526131,"remaining_time":0.7952975763},
{"learn":[4.354281355],"iteration":333,"passed_time":0.3976319234,"remaining_time":0.7928828174},
{"learn":[4.348589447],"iteration":334,"passed_time":0.398223595,"remaining_time":0.7905035543},
{"learn":[4.346355698],"iteration":335,"passed_time":0.3988112284,"remaining_time":0.7881269513},
{"learn":[4.343894047],"iteration":336,"passed_time":0.3994105545,"remaining_time":0.7857839693},
{"learn":[4.341561356],"iteration":337,"passed_time":0.4001554137,"remaining_time":0.7837363428},
{"learn":[4.338869061],"iteration":338,"passed_time":0.400788928,"remaining_time":0.7814792962},
{"learn":[4.333720063],"iteration":339,"passed_time":0.4013794343,"remaining_time":0.7791483137},
{"learn":[4.330892223],"iteration":340,"passed_time":0.4020437072,"remaining_time":0.7769700969},
{"learn":[4.328311474],"iteration":341,"passed_time":0.4027416714,"remaining_time":0.7748655549},
{"learn":[4.324580133],"iteration":342,"passed_time":0.4033566715,"remaining_time":0.7726103009},
{"learn":[4.323354432],"iteration":343,"passed_time":0.4040154087,"remaining_time":0.7704479887},
{"learn":[4.323159553],"iteration":344,"passed_time":0.4046706398,"remaining_time":0.7682877364},
{"learn":[4.318639682],"iteration":345,"passed_time":0.4052777794,"remaining_time":0.7660452824},
{"learn":[4.312712208],"iteration":346,"passed_time":0.4058479764,"remaining_time":0.7637427337},
{"learn":[4.311461062],"iteration":347,"passed_time":0.4064419888,"remaining_time":0.7614947606},
{"learn":[4.311178356],"iteration":348,"passed_time":0.4072780778,"remaining_time":0.7597078184},
{"learn":[4.311102505],"iteration":349,"passed_time":0.4080781642,"remaining_time":0.7578594477},
{"learn":[4.310232308],"iteration":350,"passed_time":0.4086877547,"remaining_time":0.7556648228},
{"learn":[4.305128197],"iteration":351,"passed_time":0.4093797778,"remaining_time":0.7536309546},
{"learn":[4.304595496],"iteration":352,"passed_time":0.4099957819,"remaining_time":0.7514653566},
{"learn":[4.3004992],"iteration":353,"passed_time":0.4105885852,"remaining_time":0.7492661753},
{"learn":[4.297581524],"iteration":354,"passed_time":0.4111834964,"remaining_time":0.7470798737},
{"learn":[4.297355825],"iteration":355,"passed_time":0.4117622476,"remaining_time":0.7448732794},
{"learn":[4.295758715],"iteration":356,"passed_time":0.4123425501,"remaining_time":0.7426785986},
{"learn":[4.292500657],"iteration":357,"passed_time":0.4129279679,"remaining_time":0.7405021101},
{"learn":[4.290797586],"iteration":358,"passed_time":0.4135170474,"remaining_time":0.7383410233},
{"learn":[4.286410608],"iteration":359,"passed_time":0.4143208602,"remaining_time":0.7365704181},
{"learn":[4.280278245],"iteration":360,"passed_time":0.414995384,"remaining_time":0.7345763168},
{"learn":[4.279941283],"iteration":361,"passed_time":0.4156096224,"remaining_time":0.7324832571},
{"learn":[4.274426275],"iteration":362,"passed_time":0.4162105595,"remaining_time":0.7303750038},
{"learn":[4.273567658],"iteration":363,"passed_time":0.4168815764,"remaining_time":0.7283974796},
{"learn":[4.269488271],"iteration":364,"passed_time":0.4174902496,"remaining_time":0.7263186534},
{"learn":[4.266838205],"iteration":365,"passed_time":0.4180910959,"remaining_time":0.7242343027},
{"learn":[4.263456509],"iteration":366,"passed_time":0.4187271898,"remaining_time":0.7222188314},
{"learn":[4.260360204],"iteration":367,"passed_time":0.4193796756,"remaining_time":0.7202390082},
{"learn":[4.255120549],"iteration":368,"passed_time":0.4200227111,"remaining_time":0.7182502187},
{"learn":[4.252582211],"iteration":369,"passed_time":0.4206232934,"remaining_time":0.7161964184},
{"learn":[4.247857931],"iteration":370,"passed_time":0.4212673613,"remaining_time":0.7142241786},
{"learn":[4.245288911],"iteration":371,"passed_time":0.4218587933,"remaining_time":0.7121702209},
{"learn":[4.24048515],"iteration":372,"passed_time":0.4225858134,"remaining_time":0.7103520242},
{"learn":[4.2378365],"iteration":373,"passed_time":0.4233279796,"remaining_time":0.7085650139},
{"learn":[4.236751063],"iteration":374,"passed_time":0.4239486214,"remaining_time":0.7065810357},
{"learn":[4.233240093],"iteration":375,"passed_time":0.4245556349,"remaining_time":0.704581692},
{"learn":[4.230358421],"iteration":376,"passed_time":0.4251309431,"remaining_time":0.702537341},
{"learn":[4.225853583],"iteration":377,"passed_time":0.4257396432,"remaining_time":0.7005557092},
{"learn":[4.224702126],"iteration":378,"passed_time":0.4263430842,"remaining_time":0.6985727052},
{"learn":[4.224361982],"iteration":379,"passed_time":0.4268963334,"remaining_time":0.6965150704},
{"learn":[4.223787954],"iteration":380,"passed_time":0.4274618557,"remaining_time":0.6944852721},
{"learn":[4.22144054],"iteration":381,"passed_time":0.4280580718,"remaining_time":0.6925127967},
{"learn":[4.217739335],"iteration":382,"passed_time":0.428781173,"remaining_time":0.6907519158},
{"learn":[4.215611665],"iteration":383,"passed_time":0.4294059625,"remaining_time":0.6888387315},
{"learn":[4.210236863],"iteration":384,"passed_time":0.430046684,"remaining_time":0.6869576901},
{"learn":[4.208454294],"iteration":385,"passed_time":0.4307146774,"remaining_time":0.6851264558},
{"learn":[4.207446501],"iteration":386,"passed_time":0.4313191829,"remaining_time":0.6832006695},
{"learn":[4.204985442],"iteration":387,"passed_time":0.4319410632,"remaining_time":0.6813090997},
{"learn":[4.202796622],"iteration":388,"passed_time":0.4325346476,"remaining_time":0.6793796136},
{"learn":[4.199774004],"iteration":389,"passed_time":0.4331066616,"remaining_time":0.6774232399},
{"learn":[4.199458358],"iteration":390,"passed_time":0.4337054993,"remaining_time":0.6755157265},
{"learn":[4.19751254],"iteration":391,"passed_time":0.4343012285,"remaining_time":0.6736100687},
{"learn":[4.195201346],"iteration":392,"passed_time":0.43489035,"remaining_time":0.6717008714},
{"learn":[4.190593508],"iteration":393,"passed_time":0.4356259227,"remaining_time":0.6700236273},
{"learn":[4.187212054],"iteration":394,"passed_time":0.4363078463,"remaining_time":0.6682689797},
{"learn":[4.184984466],"iteration":395,"passed_time":0.4370394555,"remaining_time":0.6665955331},
{"learn":[4.182832144],"iteration":396,"passed_time":0.4378417699,"remaining_time":0.6650342249},
{"learn":[4.179752812],"iteration":397,"passed_time":0.4384691154,"remaining_time":0.6632120791},
{"learn":[4.17878934],"iteration":398,"passed_time":0.4390563653,"remaining_time":0.6613355277},
{"learn":[4.174548229],"iteration":399,"passed_time":0.4396808059,"remaining_time":0.6595212088},
{"learn":[4.168872556],"iteration":400,"passed_time":0.4402811326,"remaining_time":0.657676804},
{"learn":[4.163926494],"iteration":401,"passed_time":0.4408683699,"remaining_time":0.6558191173},
{"learn":[4.159485076],"iteration":402,"passed_time":0.4414742777,"remaining_time":0.653995394},
{"learn":[4.155926102],"iteration":403,"passed_time":0.4420959134,"remaining_time":0.6522009019},
{"learn":[4.153540115],"iteration":404,"passed_time":0.4427848946,"remaining_time":0.6505111414},
{"learn":[4.150983044],"iteration":405,"passed_time":0.4434951443,"remaining_time":0.6488574279},
{"learn":[4.146539132],"iteration":406,"passed_time":0.444111214,"remaining_time":0.6470711299},
{"learn":[4.144869174],"iteration":407,"passed_time":0.4447525375,"remaining_time":0.6453272113},
{"learn":[4.142825962],"iteration":408,"passed_time":0.4453511146,"remaining_time":0.6435269162},
{"learn":[4.142467378],"iteration":409,"passed_time":0.4459155614,"remaining_time":0.6416833689},
{"learn":[4.141800768],"iteration":410,"passed_time":0.4464964323,"remaining_time":0.639869583},
{"learn":[4.140107084],"iteration":411,"passed_time":0.4470637235,"remaining_time":0.6380424016},
{"learn":[4.136243196],"iteration":412,"passed_time":0.4478108823,"remaining_time":0.6364769683},
{"learn":[4.133618439],"iteration":413,"passed_time":0.4484782653,"remaining_time":0.6348025687},
{"learn":[4.131053025],"iteration":414,"passed_time":0.4490749051,"remaining_time":0.6330333},
{"learn":[4.128379975],"iteration":415,"passed_time":0.449704102,"remaining_time":0.6313153739},
{"learn":[4.127068571],"iteration":416,"passed_time":0.4503022115,"remaining_time":0.629559207},
{"learn":[4.125969877],"iteration":417,"passed_time":0.4509305323,"remaining_time":0.6278506455},
{"learn":[4.123893633],"iteration":418,"passed_time":0.4515223452,"remaining_time":0.6260966171},
{"learn":[4.119643722],"iteration":419,"passed_time":0.4522131937,"remaining_time":0.6244848866},
{"learn":[4.11465686],"iteration":420,"passed_time":0.4530329016,"remaining_time":0.6230547507},
{"learn":[4.111565986],"iteration":421,"passed_time":0.453672869,"remaining_time":0.621381323},
{"learn":[4.106322452],"iteration":422,"passed_time":0.4542712459,"remaining_time":0.6196560494},
{"learn":[4.104222175],"iteration":423,"passed_time":0.4548997122,"remaining_time":0.6179769675},
{"learn":[4.103008002],"iteration":424,"passed_time":0.4555037736,"remaining_time":0.6162698114},
{"learn":[4.099176337],"iteration":425,"passed_time":0.456101039,"remaining_time":0.614558677},
{"learn":[4.096525716],"iteration":426,"passed_time":0.4567292219,"remaining_time":0.6128942486},
{"learn":[4.094967724],"iteration":427,"passed_time":0.457508809,"remaining_time":0.6114370065},
{"learn":[4.094683584],"iteration":428,"passed_time":0.4580940865,"remaining_time":0.6097242969},
{"learn":[4.091096563],"iteration":429,"passed_time":0.4587220676,"remaining_time":0.6080734384},
{"learn":[4.089178677],"iteration":430,"passed_time":0.4593545771,"remaining_time":0.6064333049},
{"learn":[4.085335077],"iteration":431,"passed_time":0.459975921,"remaining_time":0.6047831555},
{"learn":[4.084852122],"iteration":432,"passed_time":0.4605672471,"remaining_time":0.6030984506},
{"learn":[4.080322952],"iteration":433,"passed_time":0.4611667767,"remaining_time":0.601429483},
{"learn":[4.077449519],"iteration":434,"passed_time":0.4617418857,"remaining_time":0.5997337136},
{"learn":[4.076568374],"iteration":435,"passed_time":0.4624234645,"remaining_time":0.5981808119},
{"learn":[4.076071793],"iteration":436,"passed_time":0.4630097997,"remaining_time":0.5965091927},
{"learn":[4.075027644],"iteration":437,"passed_time":0.4635881893,"remaining_time":0.5948323343},
{"learn":[4.07020837],"iteration":438,"passed_time":0.4642685718,"remaining_time":0.5932908172},
{"learn":[4.06833694],"iteration":439,"passed_time":0.4649124942,"remaining_time":0.5917068108},
{"learn":[4.063936568],"iteration":440,"passed_time":0.4655233333,"remaining_time":0.5900851323},
{"learn":[4.061734926],"iteration":441,"passed_time":0.4661719289,"remaining_time":0.588515693},
{"learn":[4.060815619],"iteration":442,"passed_time":0.466884004,"remaining_time":0.5870302263},
{"learn":[4.056407489],"iteration":443,"passed_time":0.4677056962,"remaining_time":0.5856855114},
{"learn":[4.05238936],"iteration":444,"passed_time":0.4683567678,"remaining_time":0.5841303509},
{"learn":[4.049685254],"iteration":445,"passed_time":0.4689717293,"remaining_time":0.5825343902},
{"learn":[4.045162016],"iteration":446,"passed_time":0.4695715179,"remaining_time":0.5809240479},
{"learn":[4.042955482],"iteration":447,"passed_time":0.4701555829,"remaining_time":0.5792988432},
{"learn":[4.041467663],"iteration":448,"passed_time":0.4707508767,"remaining_time":0.5776920558},
{"learn":[4.038920476],"iteration":449,"passed_time":0.4714358717,"remaining_time":0.5761993987},
{"learn":[4.036694383],"iteration":450,"passed_time":0.4721100364,"remaining_time":0.5746971397},
{"learn":[4.034999007],"iteration":451,"passed_time":0.4726986047,"remaining_time":0.5730947685},
{"learn":[4.031928018],"iteration":452,"passed_time":0.4733727359,"remaining_time":0.571600191},
{"learn":[4.028718143],"iteration":453,"passed_time":0.4739553665,"remaining_time":0.5699991853},
{"learn":[4.027401978],"iteration":454,"passed_time":0.4745444426,"remaining_time":0.5684103763},
{"learn":[4.025930598],"iteration":455,"passed_time":0.4751884533,"remaining_time":0.5668914882},
{"learn":[4.021074523],"iteration":456,"passed_time":0.4758279675,"remaining_time":0.5653710862},
{"learn":[4.020268486],"iteration":457,"passed_time":0.4764190422,"remaining_time":0.5637972071},
{"learn":[4.017986361],"iteration":458,"passed_time":0.4770109434,"remaining_time":0.5622285846},
{"learn":[4.014814804],"iteration":459,"passed_time":0.4776142414,"remaining_time":0.5606775877},
{"learn":[4.009704796],"iteration":460,"passed_time":0.4782296191,"remaining_time":0.5591448258},
{"learn":[4.008440457],"iteration":461,"passed_time":0.4788979917,"remaining_time":0.5576777479},
{"learn":[4.004854849],"iteration":462,"passed_time":0.4795018758,"remaining_time":0.5561393246},
{"learn":[4.000898028],"iteration":463,"passed_time":0.4801270268,"remaining_time":0.5546294964},
{"learn":[3.996617985],"iteration":464,"passed_time":0.4807333466,"remaining_time":0.5531018074},
{"learn":[3.995443319],"iteration":465,"passed_time":0.4814522573,"remaining_time":0.5517070932},
{"learn":[3.990771995],"iteration":466,"passed_time":0.4821567998,"remaining_time":0.5502988743},
{"learn":[3.989249359],"iteration":467,"passed_time":0.482907843,"remaining_time":0.5489465224},
{"learn":[3.986599538],"iteration":468,"passed_time":0.4835212818,"remaining_time":0.5474409395},
{"learn":[3.985628919],"iteration":469,"passed_time":0.4841132881,"remaining_time":0.5459149844},
{"learn":[3.985086112],"iteration":470,"passed_time":0.4846865666,"remaining_time":0.5443719612},
{"learn":[3.98466839],"iteration":471,"passed_time":0.4853325826,"remaining_time":0.5429144145},
{"learn":[3.984233894],"iteration":472,"passed_time":0.4860745806,"remaining_time":0.5415672388},
{"learn":[3.981855845],"iteration":473,"passed_time":0.4869867677,"remaining_time":0.5404114764},
{"learn":[3.978684264],"iteration":474,"passed_time":0.487704915,"remaining_time":0.5390422745},
{"learn":[3.974361269],"iteration":475,"passed_time":0.4882959333,"remaining_time":0.5375358594},
{"learn":[3.972074049],"iteration":476,"passed_time":0.4888983174,"remaining_time":0.5360457443},
{"learn":[3.97191982],"iteration":477,"passed_time":0.4894963681,"remaining_time":0.5345546112},
{"learn":[3.969616848],"iteration":478,"passed_time":0.4900748991,"remaining_time":0.5330459758},
{"learn":[3.968533527],"iteration":479,"passed_time":0.490634746,"remaining_time":0.5315209748},
{"learn":[3.967568753],"iteration":480,"passed_time":0.49120639,"remaining_time":0.530012716},
{"learn":[3.966232553],"iteration":481,"passed_time":0.491842742,"remaining_time":0.5285778846},
{"learn":[3.961522393],"iteration":482,"passed_time":0.4924718876,"remaining_time":0.5271386457},
{"learn":[3.955829553],"iteration":483,"passed_time":0.4930791861,"remaining_time":0.5256794629},
{"learn":[3.954248095],"iteration":484,"passed_time":0.4936744723,"remaining_time":0.5242110376},
{"learn":[3.951922606],"iteration":485,"passed_time":0.4943100281,"remaining_time":0.5227887951},
{"learn":[3.94978202],"iteration":486,"passed_time":0.4948982247,"remaining_time":0.5213198958},
{"learn":[3.949518999],"iteration":487,"passed_time":0.495474409,"remaining_time":0.5198420029},
{"learn":[3.945431216],"iteration":488,"passed_time":0.4961250367,"remaining_time":0.5184455905},
{"learn":[3.943249086],"iteration":489,"passed_time":0.4968744294,"remaining_time":0.5171550184},
{"learn":[3.941981548],"iteration":490,"passed_time":0.4976183965,"remaining_time":0.5158610261},
{"learn":[3.936600517],"iteration":491,"passed_time":0.498214711,"remaining_time":0.5144168154},
{"learn":[3.934476885],"iteration":492,"passed_time":0.4987943534,"remaining_time":0.512958899},
{"learn":[3.93045798],"iteration":493,"passed_time":0.4994074711,"remaining_time":0.5115388266},
{"learn":[3.925977375],"iteration":494,"passed_time":0.5001199288,"remaining_time":0.5102233617},
{"learn":[3.92457993],"iteration":495,"passed_time":0.5009275982,"remaining_time":0.5090070756},
{"learn":[3.919849146],"iteration":496,"passed_time":0.5015538616,"remaining_time":0.5076088378},
{"learn":[3.919681964],"iteration":497,"passed_time":0.5021394686,"remaining_time":0.5061727173},
{"learn":[3.917633027],"iteration":498,"passed_time":0.5027069406,"remaining_time":0.5047217981},
{"learn":[3.916616419],"iteration":499,"passed_time":0.5033214237,"remaining_time":0.5033214237},
{"learn":[3.912896166],"iteration":500,"passed_time":0.5039742249,"remaining_time":0.5019623517},
{"learn":[3.912769674],"iteration":501,"passed_time":0.5045610922,"remaining_time":0.5005406851},
{"learn":[3.909373788],"iteration":502,"passed_time":0.5051623144,"remaining_time":0.4991365214},
{"learn":[3.906706036],"iteration":503,"passed_time":0.5057819591,"remaining_time":0.497753674},
{"learn":[3.903895664],"iteration":504,"passed_time":0.5063797853,"remaining_time":0.4963524628},
{"learn":[3.902982967],"iteration":505,"passed_time":0.506990114,"remaining_time":0.494966633},
{"learn":[3.900905528],"iteration":506,"passed_time":0.5075640323,"remaining_time":0.4935484575},
{"learn":[3.897463465],"iteration":507,"passed_time":0.5081691566,"remaining_time":0.4921638288},
{"learn":[3.895918033],"iteration":508,"passed_time":0.5087403853,"remaining_time":0.4907495661},
{"learn":[3.893921936],"iteration":509,"passed_time":0.5093449327,"remaining_time":0.4893706216},
{"learn":[3.890237934],"iteration":510,"passed_time":0.5099855711,"remaining_time":0.4880292451},
{"learn":[3.887311613],"iteration":511,"passed_time":0.5106543069,"remaining_time":0.4867173862},
{"learn":[3.884869735],"iteration":512,"passed_time":0.5113123563,"remaining_time":0.4853978899},
{"learn":[3.882101231],"iteration":513,"passed_time":0.5119488176,"remaining_time":0.4840605551},
{"learn":[3.88060368],"iteration":514,"passed_time":0.5126116267,"remaining_time":0.4827507552},
{"learn":[3.877726076],"iteration":515,"passed_time":0.5132181912,"remaining_time":0.4813907065},
{"learn":[3.874938145],"iteration":516,"passed_time":0.5138224629,"remaining_time":0.4800314305},
{"learn":[3.874340833],"iteration":517,"passed_time":0.5145478939,"remaining_time":0.4787878086},
{"learn":[3.873105224],"iteration":518,"passed_time":0.515269966,"remaining_time":0.4775430706},
{"learn":[3.869800236],"iteration":519,"passed_time":0.5159911831,"remaining_time":0.4762995536},
{"learn":[3.867932518],"iteration":520,"passed_time":0.5167535365,"remaining_time":0.4750958618},
{"learn":[3.866666962],"iteration":521,"passed_time":0.5173513787,"remaining_time":0.4737432165},
{"learn":[3.865527652],"iteration":522,"passed_time":0.5179579928,"remaining_time":0.4724014581},
{"learn":[3.861900081],"iteration":523,"passed_time":0.5185332237,"remaining_time":0.4710339971},
{"learn":[3.858502887],"iteration":524,"passed_time":0.5191079828,"remaining_time":0.4696691273},
{"learn":[3.858335097],"iteration":525,"passed_time":0.519656258,"remaining_time":0.4682833959},
{"learn":[3.855719306],"iteration":526,"passed_time":0.5202476555,"remaining_time":0.4669395466},
{"learn":[3.855137428],"iteration":527,"passed_time":0.5208480049,"remaining_time":0.4656065498},
{"learn":[3.851985706],"iteration":528,"passed_time":0.5215361015,"remaining_time":0.4643544496},
{"learn":[3.851051809],"iteration":529,"passed_time":0.5222028027,"remaining_time":0.4630855042},
{"learn":[3.850679146],"iteration":530,"passed_time":0.5227761896,"remaining_time":0.4617364086},
{"learn":[3.848179484],"iteration":531,"passed_time":0.5233550064,"remaining_time":0.4603950057},
{"learn":[3.844551071],"iteration":532,"passed_time":0.5239465343,"remaining_time":0.4590676013},
{"learn":[3.841604794],"iteration":533,"passed_time":0.5245498483,"remaining_time":0.4577532384},
{"learn":[3.83969656],"iteration":534,"passed_time":0.5252262126,"remaining_time":0.4565050259},
{"learn":[3.836811463],"iteration":535,"passed_time":0.5258482535,"remaining_time":0.455211921},
{"learn":[3.834182551],"iteration":536,"passed_time":0.5265775405,"remaining_time":0.4540137825},
{"learn":[3.828012842],"iteration":537,"passed_time":0.5273864055,"remaining_time":0.4528857237},
{"learn":[3.826636176],"iteration":538,"passed_time":0.527988307,"remaining_time":0.4515818359},
{"learn":[3.826189798],"iteration":539,"passed_time":0.5286986804,"remaining_time":0.45037295},
{"learn":[3.824104738],"iteration":540,"passed_time":0.5293294353,"remaining_time":0.4490983563},
{"learn":[3.82300218],"iteration":541,"passed_time":0.5299203207,"remaining_time":0.4477924482},
{"learn":[3.817146402],"iteration":542,"passed_time":0.5305249918,"remaining_time":0.4465007758},
{"learn":[3.814638044],"iteration":543,"passed_time":0.5311127126,"remaining_time":0.4451974208},
{"learn":[3.812979573],"iteration":544,"passed_time":0.5317076221,"remaining_time":0.4439026936},
{"learn":[3.811938825],"iteration":545,"passed_time":0.5322886182,"remaining_time":0.4425989609},
{"learn":[3.811479418],"iteration":546,"passed_time":0.5330126216,"remaining_time":0.4414163027},
{"learn":[3.80742981],"iteration":547,"passed_time":0.5336657776,"remaining_time":0.4401768822},
{"learn":[3.805097043],"iteration":548,"passed_time":0.5342860285,"remaining_time":0.4389125662},
{"learn":[3.801577232],"iteration":549,"passed_time":0.5348904666,"remaining_time":0.4376376545},
{"learn":[3.799762083],"iteration":550,"passed_time":0.5355959819,"remaining_time":0.4364475424},
{"learn":[3.796393455],"iteration":551,"passed_time":0.5362695312,"remaining_time":0.4352332428},
{"learn":[3.793486459],"iteration":552,"passed_time":0.5368841488,"remaining_time":0.4339732632},
{"learn":[3.792006091],"iteration":553,"passed_time":0.5374666945,"remaining_time":0.4326897938},
{"learn":[3.78932128],"iteration":554,"passed_time":0.5381648739,"remaining_time":0.4315015656},
{"learn":[3.787581812],"iteration":555,"passed_time":0.5387717159,"remaining_time":0.4302421616},
{"learn":[3.785308865],"iteration":556,"passed_time":0.5393744061,"remaining_time":0.4289817987},
{"learn":[3.78465475],"iteration":557,"passed_time":0.539945195,"remaining_time":0.4276985237},
{"learn":[3.780498869],"iteration":558,"passed_time":0.5405888871,"remaining_time":0.4264753117},
{"learn":[3.778734909],"iteration":559,"passed_time":0.5412522394,"remaining_time":0.4252696166},
{"learn":[3.778652349],"iteration":560,"passed_time":0.5419708348,"remaining_time":0.4241090846},
{"learn":[3.777928006],"iteration":561,"passed_time":0.5426302152,"remaining_time":0.4229039755},
{"learn":[3.776131406],"iteration":562,"passed_time":0.5432256317,"remaining_time":0.4216511564},
{"learn":[3.772925617],"iteration":563,"passed_time":0.5438228676,"remaining_time":0.420402075},
{"learn":[3.7727745],"iteration":564,"passed_time":0.5443913595,"remaining_time":0.4191331706},
{"learn":[3.771763073],"iteration":565,"passed_time":0.5449839543,"remaining_time":0.4178852229},
{"learn":[3.768738162],"iteration":566,"passed_time":0.5455651043,"remaining_time":0.4166308469},
{"learn":[3.767220794],"iteration":567,"passed_time":0.5461581557,"remaining_time":0.4153878931},
{"learn":[3.766691102],"iteration":568,"passed_time":0.5468042465,"remaining_time":0.4141873994},
{"learn":[3.766259335],"iteration":569,"passed_time":0.5474736668,"remaining_time":0.4130064504},
{"learn":[3.76116362],"iteration":570,"passed_time":0.548104583,"remaining_time":0.4117983645},
{"learn":[3.758633056],"iteration":571,"passed_time":0.5487384463,"remaining_time":0.4105945018},
{"learn":[3.754603809],"iteration":572,"passed_time":0.5493377826,"remaining_time":0.409366899},
{"learn":[3.754070549],"iteration":573,"passed_time":0.5499147051,"remaining_time":0.4081248508},
{"learn":[3.750534319],"iteration":574,"passed_time":0.5505561035,"remaining_time":0.4069327721},
{"learn":[3.746491516],"iteration":575,"passed_time":0.5511378916,"remaining_time":0.4056987258},
{"learn":[3.744210544],"iteration":576,"passed_time":0.551734835,"remaining_time":0.4044780506},
{"learn":[3.742929991],"iteration":577,"passed_time":0.5523224305,"remaining_time":0.4032527087},
{"learn":[3.740402992],"iteration":578,"passed_time":0.5529976076,"remaining_time":0.4020932518},
{"learn":[3.739644243],"iteration":579,"passed_time":0.5536031093,"remaining_time":0.4008850102},
{"learn":[3.737529404],"iteration":580,"passed_time":0.5541965483,"remaining_time":0.3996701441},
{"learn":[3.737196923],"iteration":581,"passed_time":0.5547894542,"remaining_time":0.3984570307},
{"learn":[3.733954464],"iteration":582,"passed_time":0.5553737033,"remaining_time":0.397239853},
{"learn":[3.731608623],"iteration":583,"passed_time":0.5560201406,"remaining_time":0.3960691412},
{"learn":[3.729843952],"iteration":584,"passed_time":0.5568158355,"remaining_time":0.3950061055},
{"learn":[3.727223798],"iteration":585,"passed_time":0.5576874537,"remaining_time":0.3939976209},
{"learn":[3.725351667],"iteration":586,"passed_time":0.5584087229,"remaining_time":0.3928838204},
{"learn":[3.725026912],"iteration":587,"passed_time":0.559038172,"remaining_time":0.3917070185},
{"learn":[3.721974565],"iteration":588,"passed_time":0.5596415785,"remaining_time":0.3905139028},
{"learn":[3.720269493],"iteration":589,"passed_time":0.5602757268,"remaining_time":0.3893441491},
{"learn":[3.718907466],"iteration":590,"passed_time":0.5608766168,"remaining_time":0.3881531917},
{"learn":[3.715602912],"iteration":591,"passed_time":0.5614853623,"remaining_time":0.3869696416},
{"learn":[3.714463059],"iteration":592,"passed_time":0.5620590293,"remaining_time":0.3857639544},
{"learn":[3.710802077],"iteration":593,"passed_time":0.5626446868,"remaining_time":0.3845685906},
{"learn":[3.708032435],"iteration":594,"passed_time":0.5632404404,"remaining_time":0.3833821485},
{"learn":[3.703788939],"iteration":595,"passed_time":0.5638149936,"remaining_time":0.3821833178},
{"learn":[3.702500944],"iteration":596,"passed_time":0.5643886647,"remaining_time":0.3809859831},
{"learn":[3.698196925],"iteration":597,"passed_time":0.5650257163,"remaining_time":0.379833341},
{"learn":[3.69658891],"iteration":598,"passed_time":0.5656663403,"remaining_time":0.3786848121},
{"learn":[3.696124066],"iteration":599,"passed_time":0.5662913501,"remaining_time":0.3775275667},
{"learn":[3.693537052],"iteration":600,"passed_time":0.5668676697,"remaining_time":0.3763397674},
{"learn":[3.691343275],"iteration":601,"passed_time":0.5674515876,"remaining_time":0.375159023},
{"learn":[3.690973831],"iteration":602,"passed_time":0.5681757684,"remaining_time":0.3740726037},
{"learn":[3.686151073],"iteration":603,"passed_time":0.5687669397,"remaining_time":0.372900179},
{"learn":[3.683921982],"iteration":604,"passed_time":0.5693894355,"remaining_time":0.3717501273},
{"learn":[3.679975271],"iteration":605,"passed_time":0.5700028399,"remaining_time":0.3705959058},
{"learn":[3.674047638],"iteration":606,"passed_time":0.5706372194,"remaining_time":0.3694570465},
{"learn":[3.673151794],"iteration":607,"passed_time":0.5714563471,"remaining_time":0.3684389606},
{"learn":[3.670953108],"iteration":608,"passed_time":0.5721688267,"remaining_time":0.3673530562},
{"learn":[3.6703947],"iteration":609,"passed_time":0.5728269559,"remaining_time":0.3662336276},
{"learn":[3.668433805],"iteration":610,"passed_time":0.5734288398,"remaining_time":0.3650798996},
{"learn":[3.668304956],"iteration":611,"passed_time":0.5740071143,"remaining_time":0.3639130071},
{"learn":[3.667880012],"iteration":612,"passed_time":0.5745949309,"remaining_time":0.3627540591},
{"learn":[3.667282264],"iteration":613,"passed_time":0.5752635893,"remaining_time":0.3616477939},
{"learn":[3.664611483],"iteration":614,"passed_time":0.5759226149,"remaining_time":0.3605369215},
{"learn":[3.662543394],"iteration":615,"passed_time":0.5765440017,"remaining_time":0.359404053},
{"learn":[3.659041959],"iteration":616,"passed_time":0.5771683875,"remaining_time":0.3582747041},
{"learn":[3.656868545],"iteration":617,"passed_time":0.5778225037,"remaining_time":0.3571653664},
{"learn":[3.654785614],"iteration":618,"passed_time":0.5784349437,"remaining_time":0.3560318474},
{"learn":[3.654566096],"iteration":619,"passed_time":0.5790280556,"remaining_time":0.3548881631},
{"learn":[3.651007045],"iteration":620,"passed_time":0.5796232913,"remaining_time":0.3537475481},
{"learn":[3.648921786],"iteration":621,"passed_time":0.5802326228,"remaining_time":0.3526172531},
{"learn":[3.647655706],"iteration":622,"passed_time":0.5808222581,"remaining_time":0.3514767115},
{"learn":[3.647241144],"iteration":623,"passed_time":0.5814206619,"remaining_time":0.3503432193},
{"learn":[3.644195689],"iteration":624,"passed_time":0.5819970236,"remaining_time":0.3491982142},
{"learn":[3.642632246],"iteration":625,"passed_time":0.5825880739,"remaining_time":0.3480638013},
{"learn":[3.642523322],"iteration":626,"passed_time":0.5830421428,"remaining_time":0.346849632},
{"learn":[3.641494659],"iteration":627,"passed_time":0.5836244363,"remaining_time":0.345713838},
{"learn":[3.63976496],"iteration":628,"passed_time":0.5842540182,"remaining_time":0.344607696},
{"learn":[3.637945652],"iteration":629,"passed_time":0.5849832858,"remaining_time":0.3435616123},
{"learn":[3.636233667],"iteration":630,"passed_time":0.5858428235,"remaining_time":0.342592713},
{"learn":[3.635304404],"iteration":631,"passed_time":0.5866082669,"remaining_time":0.3415693706},
{"learn":[3.632234951],"iteration":632,"passed_time":0.5873428138,"remaining_time":0.34052893},
{"learn":[3.631630987],"iteration":633,"passed_time":0.587964336,"remaining_time":0.3394242066},
{"learn":[3.630301009],"iteration":634,"passed_time":0.5885596415,"remaining_time":0.3383059357},
{"learn":[3.629077964],"iteration":635,"passed_time":0.5891390056,"remaining_time":0.3371801856},
{"learn":[3.628004522],"iteration":636,"passed_time":0.5897172818,"remaining_time":0.3360555311},
{"learn":[3.625062876],"iteration":637,"passed_time":0.5903162237,"remaining_time":0.334944315},
{"learn":[3.624917986],"iteration":638,"passed_time":0.5908877601,"remaining_time":0.3338192197},
{"learn":[3.622887087],"iteration":639,"passed_time":0.5914955707,"remaining_time":0.3327162585},
{"learn":[3.621220865],"iteration":640,"passed_time":0.5920912411,"remaining_time":0.331608043},
{"learn":[3.621143844],"iteration":641,"passed_time":0.5926560495,"remaining_time":0.3304842145},
{"learn":[3.620822821],"iteration":642,"passed_time":0.5932151288,"remaining_time":0.329358944},
{"learn":[3.619202826],"iteration":643,"passed_time":0.5937960602,"remaining_time":0.3282475115},
{"learn":[3.618204882],"iteration":644,"passed_time":0.5943798065,"remaining_time":0.3271392734},
{"learn":[3.614259666],"iteration":645,"passed_time":0.5949721399,"remaining_time":0.3260373646},
{"learn":[3.613415661],"iteration":646,"passed_time":0.5955812091,"remaining_time":0.324946162},
{"learn":[3.611096773],"iteration":647,"passed_time":0.5961799778,"remaining_time":0.3238508521},
{"learn":[3.610820695],"iteration":648,"passed_time":0.5968141101,"remaining_time":0.3227761982},
{"learn":[3.609290065],"iteration":649,"passed_time":0.5973958596,"remaining_time":0.3216746936},
{"learn":[3.60897947],"iteration":650,"passed_time":0.5979827362,"remaining_time":0.3205775345},
{"learn":[3.606570702],"iteration":651,"passed_time":0.598568809,"remaining_time":0.3194815115},
{"learn":[3.606292637],"iteration":652,"passed_time":0.5991838545,"remaining_time":0.3184024464},
{"learn":[3.602753838],"iteration":653,"passed_time":0.5998826435,"remaining_time":0.317369105},
{"learn":[3.599755869],"iteration":654,"passed_time":0.6006979179,"remaining_time":0.31639814},
{"learn":[3.599509575],"iteration":655,"passed_time":0.601495941,"remaining_time":0.3154186032},
{"learn":[3.595337722],"iteration":656,"passed_time":0.6021982857,"remaining_time":0.3143896682},
{"learn":[3.595168561],"iteration":657,"passed_time":0.6028104482,"remaining_time":0.313314853},
{"learn":[3.59290559],"iteration":658,"passed_time":0.6034658188,"remaining_time":0.3122638},
{"learn":[3.592015928],"iteration":659,"passed_time":0.6040815051,"remaining_time":0.3111935026},
{"learn":[3.590680403],"iteration":660,"passed_time":0.6046715742,"remaining_time":0.3101114427},
{"learn":[3.590361532],"iteration":661,"passed_time":0.6053304147,"remaining_time":0.3090659821},
{"learn":[3.589069739],"iteration":662,"passed_time":0.605927237,"remaining_time":0.3079901642},
{"learn":[3.585010186],"iteration":663,"passed_time":0.606545153,"remaining_time":0.306926463},
{"learn":[3.582997552],"iteration":664,"passed_time":0.6073400257,"remaining_time":0.305953246},
{"learn":[3.582119256],"iteration":665,"passed_time":0.6079986409,"remaining_time":0.3049122313},
{"learn":[3.579019356],"iteration":666,"passed_time":0.608593986,"remaining_time":0.3038407756},
{"learn":[3.57719559],"iteration":667,"passed_time":0.6092078805,"remaining_time":0.3027799646},
{"learn":[3.574050046],"iteration":668,"passed_time":0.609885506,"remaining_time":0.3017520216},
{"learn":[3.572204518],"iteration":669,"passed_time":0.6104775223,"remaining_time":0.3006829588},
{"learn":[3.569508025],"iteration":670,"passed_time":0.6110953643,"remaining_time":0.2996279804},
{"learn":[3.566268704],"iteration":671,"passed_time":0.6116993249,"remaining_time":0.2985675276},
{"learn":[3.562564052],"iteration":672,"passed_time":0.612439358,"remaining_time":0.2975745469},
{"learn":[3.561173586],"iteration":673,"passed_time":0.6131703862,"remaining_time":0.2965779613},
{"learn":[3.559551904],"iteration":674,"passed_time":0.6138262772,"remaining_time":0.2955459853},
{"learn":[3.558593054],"iteration":675,"passed_time":0.6144776449,"remaining_time":0.2945129541},
{"learn":[3.555647008],"iteration":676,"passed_time":0.6151011488,"remaining_time":0.2934677564},
{"learn":[3.553100059],"iteration":677,"passed_time":0.6157913062,"remaining_time":0.2924554581},
{"learn":[3.55085578],"iteration":678,"passed_time":0.616475003,"remaining_time":0.2914410545},
{"learn":[3.550737965],"iteration":679,"passed_time":0.617047978,"remaining_time":0.2903755191},
{"learn":[3.549408772],"iteration":680,"passed_time":0.6176501932,"remaining_time":0.2893251272},
{"learn":[3.547390589],"iteration":681,"passed_time":0.6182467985,"remaining_time":0.2882734339},
{"learn":[3.54723575],"iteration":682,"passed_time":0.6188064907,"remaining_time":0.2872059408},
{"learn":[3.543988891],"iteration":683,"passed_time":0.6193957417,"remaining_time":0.2861535883},
{"learn":[3.543868508],"iteration":684,"passed_time":0.6199777056,"remaining_time":0.2850992369},
{"learn":[3.542752124],"iteration":685,"passed_time":0.6205611879,"remaining_time":0.2840469577},
{"learn":[3.541334315],"iteration":686,"passed_time":0.6212329027,"remaining_time":0.2830362424},
{"learn":[3.540208266],"iteration":687,"passed_time":0.6219918703,"remaining_time":0.2820660807},
{"learn":[3.537730983],"iteration":688,"passed_time":0.6226188265,"remaining_time":0.2810369449},
{"learn":[3.53419867],"iteration":689,"passed_time":0.6232142396,"remaining_time":0.2799948033},
{"learn":[3.532628335],"iteration":690,"passed_time":0.6238124139,"remaining_time":0.2789551894},
{"learn":[3.532204987],"iteration":691,"passed_time":0.6244046698,"remaining_time":0.2779142172},
{"learn":[3.530618147],"iteration":692,"passed_time":0.6249795341,"remaining_time":0.2768668354},
{"learn":[3.528909306],"iteration":693,"passed_time":0.6255627129,"remaining_time":0.2758244815},
{"learn":[3.526700678],"iteration":694,"passed_time":0.6262103516,"remaining_time":0.2748117371},
{"learn":[3.526439574],"iteration":695,"passed_time":0.626823001,"remaining_time":0.273784759},
{"learn":[3.525784216],"iteration":696,"passed_time":0.6274296067,"remaining_time":0.2727563426},
{"learn":[3.524112693],"iteration":697,"passed_time":0.6280421046,"remaining_time":0.2717316842},
{"learn":[3.522813541],"iteration":698,"passed_time":0.6287953465,"remaining_time":0.2707688116},
{"learn":[3.519148203],"iteration":699,"passed_time":0.6294625848,"remaining_time":0.2697696792},
{"learn":[3.517236747],"iteration":700,"passed_time":0.6300564946,"remaining_time":0.2687402167},
{"learn":[3.515603888],"iteration":701,"passed_time":0.6308705491,"remaining_time":0.2678054468},
{"learn":[3.51263524],"iteration":702,"passed_time":0.6315949729,"remaining_time":0.2668331535},
{"learn":[3.51123442],"iteration":703,"passed_time":0.6321991849,"remaining_time":0.2658110209},
{"learn":[3.50828027],"iteration":704,"passed_time":0.6327913467,"remaining_time":0.2647850316},
{"learn":[3.508265537],"iteration":705,"passed_time":0.6331616671,"remaining_time":0.2636678897},
{"learn":[3.506774876],"iteration":706,"passed_time":0.6337468806,"remaining_time":0.262641918},
{"learn":[3.50552068],"iteration":707,"passed_time":0.63436245,"remaining_time":0.261629711},
{"learn":[3.501973993],"iteration":708,"passed_time":0.6349588771,"remaining_time":0.2606107662},
{"learn":[3.498880354],"iteration":709,"passed_time":0.6356832328,"remaining_time":0.2596452641},
{"learn":[3.497370959],"iteration":710,"passed_time":0.6363385001,"remaining_time":0.258652358},
{"learn":[3.496050455],"iteration":711,"passed_time":0.6369372772,"remaining_time":0.2576375503},
{"learn":[3.495630067],"iteration":712,"passed_time":0.6375227059,"remaining_time":0.2566185366},
{"learn":[3.49550669],"iteration":713,"passed_time":0.6381014689,"remaining_time":0.2555980674},
{"learn":[3.493652375],"iteration":714,"passed_time":0.6387129773,"remaining_time":0.2545918861},
{"learn":[3.491915684],"iteration":715,"passed_time":0.6393131182,"remaining_time":0.2535822983},
{"learn":[3.490303956],"iteration":716,"passed_time":0.6399599363,"remaining_time":0.2525922761},
{"learn":[3.488363853],"iteration":717,"passed_time":0.6406335546,"remaining_time":0.2516137359},
{"learn":[3.485483936],"iteration":718,"passed_time":0.6412604141,"remaining_time":0.2506177696},
{"learn":[3.483763466],"iteration":719,"passed_time":0.641996112,"remaining_time":0.2496651547},
{"learn":[3.481642352],"iteration":720,"passed_time":0.6426648007,"remaining_time":0.2486872114},
{"learn":[3.479826119],"iteration":721,"passed_time":0.6433537542,"remaining_time":0.2477179275},
{"learn":[3.478588728],"iteration":722,"passed_time":0.6439594106,"remaining_time":0.2467175059},
{"learn":[3.475390887],"iteration":723,"passed_time":0.6446834216,"remaining_time":0.2457632933},
{"learn":[3.472636852],"iteration":724,"passed_time":0.6454090637,"remaining_time":0.2448103345},
{"learn":[3.47061883],"iteration":725,"passed_time":0.6463704353,"remaining_time":0.2439469687},
{"learn":[3.46953149],"iteration":726,"passed_time":0.6470374424,"remaining_time":0.2429727948},
{"learn":[3.467217162],"iteration":727,"passed_time":0.6476333928,"remaining_time":0.241972916},
{"learn":[3.465686216],"iteration":728,"passed_time":0.648243867,"remaining_time":0.2409795445},
{"learn":[3.462631216],"iteration":729,"passed_time":0.648846928,"remaining_time":0.2399844802},
{"learn":[3.461451053],"iteration":730,"passed_time":0.649457514,"remaining_time":0.2389932575},
{"learn":[3.458950469],"iteration":731,"passed_time":0.6501614755,"remaining_time":0.2380372615},
{"learn":[3.458072145],"iteration":732,"passed_time":0.6507512032,"remaining_time":0.2370403428},
{"learn":[3.454364268],"iteration":733,"passed_time":0.651332888,"remaining_time":0.2360416188},
{"learn":[3.453243406],"iteration":734,"passed_time":0.6519549079,"remaining_time":0.2350585722},
{"learn":[3.453017963],"iteration":735,"passed_time":0.6525398414,"remaining_time":0.234063204},
{"learn":[3.45201581],"iteration":736,"passed_time":0.6531613905,"remaining_time":0.2330820159},
{"learn":[3.449510107],"iteration":737,"passed_time":0.6537846959,"remaining_time":0.2321024259},
{"learn":[3.447189189],"iteration":738,"passed_time":0.6544721376,"remaining_time":0.2311464518},
{"learn":[3.446423605],"iteration":739,"passed_time":0.6550772862,"remaining_time":0.2301622898},
{"learn":[3.445531987],"iteration":740,"passed_time":0.6556624779,"remaining_time":0.2291721751},
{"learn":[3.445328199],"iteration":741,"passed_time":0.65624922,"remaining_time":0.228183691},
{"learn":[3.443327544],"iteration":742,"passed_time":0.6569500992,"remaining_time":0.2272357678},
{"learn":[3.441475798],"iteration":743,"passed_time":0.6576558944,"remaining_time":0.2262902002},
{"learn":[3.439046501],"iteration":744,"passed_time":0.6582509233,"remaining_time":0.225307363},
{"learn":[3.435899469],"iteration":745,"passed_time":0.6588368767,"remaining_time":0.2243224755},
{"learn":[3.433988352],"iteration":746,"passed_time":0.6595011942,"remaining_time":0.223365197},
{"learn":[3.433413263],"iteration":747,"passed_time":0.6602143212,"remaining_time":0.2224251456},
{"learn":[3.429944699],"iteration":748,"passed_time":0.6610125763,"remaining_time":0.2215142278},
{"learn":[3.429291634],"iteration":749,"passed_time":0.661638384,"remaining_time":0.220546128},
{"learn":[3.429175603],"iteration":750,"passed_time":0.662253353,"remaining_time":0.2195753461},
{"learn":[3.428780323],"iteration":751,"passed_time":0.6628549048,"remaining_time":0.2186010856},
{"learn":[3.423893341],"iteration":752,"passed_time":0.663497804,"remaining_time":0.2176413779},
{"learn":[3.421024316],"iteration":753,"passed_time":0.6642646725,"remaining_time":0.2167229568},
{"learn":[3.420969872],"iteration":754,"passed_time":0.6648910174,"remaining_time":0.2157593368},
{"learn":[3.419544785],"iteration":755,"passed_time":0.6655030597,"remaining_time":0.2147919928},
{"learn":[3.417057977],"iteration":756,"passed_time":0.6661160159,"remaining_time":0.2138258809},
{"learn":[3.415160245],"iteration":757,"passed_time":0.666758419,"remaining_time":0.2128701021},
{"learn":[3.412854597],"iteration":758,"passed_time":0.6673919501,"remaining_time":0.211912332},
{"learn":[3.410926347],"iteration":759,"passed_time":0.6680800123,"remaining_time":0.2109726355},
{"learn":[3.408963843],"iteration":760,"passed_time":0.6689193325,"remaining_time":0.2100811044},
{"learn":[3.407629634],"iteration":761,"passed_time":0.6695600297,"remaining_time":0.2091276733},
{"learn":[3.404384724],"iteration":762,"passed_time":0.6701573278,"remaining_time":0.2081615815},
{"learn":[3.403041656],"iteration":763,"passed_time":0.6707510174,"remaining_time":0.2071953404},
{"learn":[3.401101731],"iteration":764,"passed_time":0.6716497476,"remaining_time":0.2063237787},
{"learn":[3.400890668],"iteration":765,"passed_time":0.672493244,"remaining_time":0.205435273},
{"learn":[3.399289941],"iteration":766,"passed_time":0.6731460334,"remaining_time":0.2044889515},
{"learn":[3.399202366],"iteration":767,"passed_time":0.6737313091,"remaining_time":0.2035229996},
{"learn":[3.397447845],"iteration":768,"passed_time":0.6744297668,"remaining_time":0.2025920366},
{"learn":[3.394655341],"iteration":769,"passed_time":0.6752650167,"remaining_time":0.2017025375},
{"learn":[3.393228229],"iteration":770,"passed_time":0.6760343706,"remaining_time":0.2007936068},
{"learn":[3.389691197],"iteration":771,"passed_time":0.676671164,"remaining_time":0.1998458878},
{"learn":[3.389626772],"iteration":772,"passed_time":0.6772353948,"remaining_time":0.1988776644},
{"learn":[3.388480222],"iteration":773,"passed_time":0.6778332403,"remaining_time":0.1979203001},
{"learn":[3.388215066],"iteration":774,"passed_time":0.6784431831,"remaining_time":0.1969673757},
{"learn":[3.386324358],"iteration":775,"passed_time":0.6790445423,"remaining_time":0.1960128576},
{"learn":[3.383913061],"iteration":776,"passed_time":0.6796322387,"remaining_time":0.1950553272},
{"learn":[3.382839768],"iteration":777,"passed_time":0.680218805,"remaining_time":0.1940984251},
{"learn":[3.381961844],"iteration":778,"passed_time":0.680815154,"remaining_time":0.1931452491},
{"learn":[3.381521703],"iteration":779,"passed_time":0.6814572998,"remaining_time":0.1922059051},
{"learn":[3.380918963],"iteration":780,"passed_time":0.6820454998,"remaining_time":0.1912521952},
{"learn":[3.377139006],"iteration":781,"passed_time":0.6826954491,"remaining_time":0.1903166341},
{"learn":[3.376004372],"iteration":782,"passed_time":0.6833149147,"remaining_time":0.1893733544},
{"learn":[3.373826468],"iteration":783,"passed_time":0.6839061684,"remaining_time":0.188423128},
{"learn":[3.373546786],"iteration":784,"passed_time":0.684527905,"remaining_time":0.1874821651},
{"learn":[3.372109181],"iteration":785,"passed_time":0.6852253083,"remaining_time":0.1865626158},
{"learn":[3.370764924],"iteration":786,"passed_time":0.6859022528,"remaining_time":0.1856380938},
{"learn":[3.367833107],"iteration":787,"passed_time":0.6865708406,"remaining_time":0.184711952},
{"learn":[3.36450404],"iteration":788,"passed_time":0.6871694782,"remaining_time":0.1837677565},
{"learn":[3.361794558],"iteration":789,"passed_time":0.687775159,"remaining_time":0.1828263081},
{"learn":[3.356880529],"iteration":790,"passed_time":0.6883860527,"remaining_time":0.181887086},
{"learn":[3.353843509],"iteration":791,"passed_time":0.6890321268,"remaining_time":0.1809579323},
{"learn":[3.353640253],"iteration":792,"passed_time":0.6897036708,"remaining_time":0.1800361411},
{"learn":[3.353055088],"iteration":793,"passed_time":0.6904907712,"remaining_time":0.1791449608},
{"learn":[3.351415617],"iteration":794,"passed_time":0.6912930891,"remaining_time":0.1782579664},
{"learn":[3.349169061],"iteration":795,"passed_time":0.6919494754,"remaining_time":0.1773337852},
{"learn":[3.346211014],"iteration":796,"passed_time":0.6925671585,"remaining_time":0.176400418},
{"learn":[3.344560452],"iteration":797,"passed_time":0.6932583173,"remaining_time":0.1754864412},
{"learn":[3.344445461],"iteration":798,"passed_time":0.6939193221,"remaining_time":0.1745654365},
{"learn":[3.342608898],"iteration":799,"passed_time":0.694580131,"remaining_time":0.1736450327},
{"learn":[3.339572899],"iteration":800,"passed_time":0.6951656497,"remaining_time":0.1727065721},
{"learn":[3.339309302],"iteration":801,"passed_time":0.6957628764,"remaining_time":0.1717718822},
{"learn":[3.33698088],"iteration":802,"passed_time":0.6964647141,"remaining_time":0.170863697},
{"learn":[3.334746342],"iteration":803,"passed_time":0.6970989271,"remaining_time":0.1699395394},
{"learn":[3.332048511],"iteration":804,"passed_time":0.6976903902,"remaining_time":0.1690057467},
{"learn":[3.331932544],"iteration":805,"passed_time":0.6982448561,"remaining_time":0.1680638984},
{"learn":[3.330541133],"iteration":806,"passed_time":0.6988388441,"remaining_time":0.1671324621},
{"learn":[3.329124989],"iteration":807,"passed_time":0.6995671843,"remaining_time":0.1662337864},
{"learn":[3.32583918],"iteration":808,"passed_time":0.7003487615,"remaining_time":0.1653481007},
{"learn":[3.325287299],"iteration":809,"passed_time":0.7009408048,"remaining_time":0.1644182135},
{"learn":[3.322745162],"iteration":810,"passed_time":0.7015405757,"remaining_time":0.1634909603},
{"learn":[3.319733662],"iteration":811,"passed_time":0.7021765897,"remaining_time":0.162572905},
{"learn":[3.318080007],"iteration":812,"passed_time":0.702869684,"remaining_time":0.1616686727},
{"learn":[3.317179538],"iteration":813,"passed_time":0.7035642539,"remaining_time":0.1607652964},
{"learn":[3.315685949],"iteration":814,"passed_time":0.7042082706,"remaining_time":0.1598509571},
{"learn":[3.314944576],"iteration":815,"passed_time":0.7049296936,"remaining_time":0.1589547348},
{"learn":[3.312369052],"iteration":816,"passed_time":0.7056366113,"remaining_time":0.1580556914},
{"learn":[3.312321621],"iteration":817,"passed_time":0.7061035241,"remaining_time":0.1571037181},
{"learn":[3.309465776],"iteration":818,"passed_time":0.7066797816,"remaining_time":0.1561770946},
{"learn":[3.308307377],"iteration":819,"passed_time":0.7073143746,"remaining_time":0.155264131},
{"learn":[3.308076804],"iteration":820,"passed_time":0.7078829489,"remaining_time":0.1543374517},
{"learn":[3.305643326],"iteration":821,"passed_time":0.7084632775,"remaining_time":0.153414189},
{"learn":[3.304154814],"iteration":822,"passed_time":0.7090486625,"remaining_time":0.1524928472},
{"learn":[3.303076321],"iteration":823,"passed_time":0.7096979055,"remaining_time":0.1515859604},
{"learn":[3.301746372],"iteration":824,"passed_time":0.7102819697,"remaining_time":0.1506658724},
{"learn":[3.301345455],"iteration":825,"passed_time":0.7108620233,"remaining_time":0.1497457531},
{"learn":[3.299181039],"iteration":826,"passed_time":0.7114425048,"remaining_time":0.1488265457},
{"learn":[3.297989357],"iteration":827,"passed_time":0.7120434915,"remaining_time":0.1479124161},
{"learn":[3.294775182],"iteration":828,"passed_time":0.7126356559,"remaining_time":0.1469972221},
{"learn":[3.293840636],"iteration":829,"passed_time":0.7132263253,"remaining_time":0.1460825004},
{"learn":[3.289279397],"iteration":830,"passed_time":0.7139304709,"remaining_time":0.1451916361},
{"learn":[3.286204979],"iteration":831,"passed_time":0.7146139903,"remaining_time":0.1442970557},
{"learn":[3.284833593],"iteration":832,"passed_time":0.7151969186,"remaining_time":0.1433828156},
{"learn":[3.283519914],"iteration":833,"passed_time":0.7158526844,"remaining_time":0.1424838676},
{"learn":[3.282853026],"iteration":834,"passed_time":0.7164805427,"remaining_time":0.1415799875},
{"learn":[3.281944673],"iteration":835,"passed_time":0.7170477919,"remaining_time":0.1406648778},
{"learn":[3.279764865],"iteration":836,"passed_time":0.7176348106,"remaining_time":0.1397544494},
{"learn":[3.277468839],"iteration":837,"passed_time":0.7182080707,"remaining_time":0.138842133},
{"learn":[3.277124974],"iteration":838,"passed_time":0.7188157887,"remaining_time":0.1379372372},
{"learn":[3.275636037],"iteration":839,"passed_time":0.7194956196,"remaining_time":0.1370467847},
{"learn":[3.274413635],"iteration":840,"passed_time":0.720249862,"remaining_time":0.1361709014},
{"learn":[3.272636087],"iteration":841,"passed_time":0.7209336547,"remaining_time":0.1352820872},
{"learn":[3.269644466],"iteration":842,"passed_time":0.7216552282,"remaining_time":0.1344007958},
{"learn":[3.26852083],"iteration":843,"passed_time":0.7222452838,"remaining_time":0.1334955738},
{"learn":[3.267820927],"iteration":844,"passed_time":0.7228608986,"remaining_time":0.1325957861},
{"learn":[3.267331099],"iteration":845,"passed_time":0.7236753667,"remaining_time":0.1317328682},
{"learn":[3.267231014],"iteration":846,"passed_time":0.7244830412,"remaining_time":0.1308688374},
{"learn":[3.267158695],"iteration":847,"passed_time":0.7253439116,"remaining_time":0.1300144747},
{"learn":[3.264718705],"iteration":848,"passed_time":0.7260998112,"remaining_time":0.129141427},
{"learn":[3.261678512],"iteration":849,"passed_time":0.7268452908,"remaining_time":0.128266816},
{"learn":[3.261368381],"iteration":850,"passed_time":0.7274667701,"remaining_time":0.1273707976},
{"learn":[3.260128799],"iteration":851,"passed_time":0.7280583972,"remaining_time":0.126470238},
{"learn":[3.258972952],"iteration":852,"passed_time":0.7286354777,"remaining_time":0.1255678959},
{"learn":[3.258724846],"iteration":853,"passed_time":0.7292134403,"remaining_time":0.1246664664},
{"learn":[3.25686724],"iteration":854,"passed_time":0.7298325183,"remaining_time":0.1237727663},
{"learn":[3.255750259],"iteration":855,"passed_time":0.7304152035,"remaining_time":0.1228735856},
{"learn":[3.254915866],"iteration":856,"passed_time":0.7309977652,"remaining_time":0.121975123},
{"learn":[3.254348625],"iteration":857,"passed_time":0.7316318908,"remaining_time":0.1210859306},
{"learn":[3.253408514],"iteration":858,"passed_time":0.7322752205,"remaining_time":0.1201988429},
{"learn":[3.253291714],"iteration":859,"passed_time":0.7328676951,"remaining_time":0.1193040434},
{"learn":[3.250186342],"iteration":860,"passed_time":0.7334807135,"remaining_time":0.1184132627},
{"learn":[3.249141318],"iteration":861,"passed_time":0.7342076731,"remaining_time":0.1175413676},
{"learn":[3.246300388],"iteration":862,"passed_time":0.7350312226,"remaining_time":0.1166851419},
{"learn":[3.245205135],"iteration":863,"passed_time":0.7357508606,"remaining_time":0.1158126355},
{"learn":[3.244403535],"iteration":864,"passed_time":0.7366054393,"remaining_time":0.1149615426},
{"learn":[3.244211781],"iteration":865,"passed_time":0.7372386392,"remaining_time":0.1140761867},
{"learn":[3.242286347],"iteration":866,"passed_time":0.7380108064,"remaining_time":0.1132127304},
{"learn":[3.239606746],"iteration":867,"passed_time":0.7387194107,"remaining_time":0.1123398182},
{"learn":[3.236773361],"iteration":868,"passed_time":0.7393048723,"remaining_time":0.1114487207},
{"learn":[3.234552446],"iteration":869,"passed_time":0.7398888011,"remaining_time":0.1105580967},
{"learn":[3.233724647],"iteration":870,"passed_time":0.7405270575,"remaining_time":0.1096762232},
{"learn":[3.230851485],"iteration":871,"passed_time":0.7412253067,"remaining_time":0.1088037147},
{"learn":[3.227728941],"iteration":872,"passed_time":0.7418803015,"remaining_time":0.107925313},
{"learn":[3.225787575],"iteration":873,"passed_time":0.7424667972,"remaining_time":0.1070375474},
{"learn":[3.222797487],"iteration":874,"passed_time":0.74306302,"remaining_time":0.10615186},
{"learn":[3.22137014],"iteration":875,"passed_time":0.7436493711,"remaining_time":0.1052654361},
{"learn":[3.219701963],"iteration":876,"passed_time":0.7442161772,"remaining_time":0.1043769553},
{"learn":[3.21783327],"iteration":877,"passed_time":0.7447945509,"remaining_time":0.1034908146},
{"learn":[3.217713355],"iteration":878,"passed_time":0.7453611174,"remaining_time":0.1026037488},
{"learn":[3.217666091],"iteration":879,"passed_time":0.7459209105,"remaining_time":0.1017164878},
{"learn":[3.214962005],"iteration":880,"passed_time":0.7465145118,"remaining_time":0.1008345368},
{"learn":[3.214081828],"iteration":881,"passed_time":0.7471360415,"remaining_time":0.09995697607},
{"learn":[3.213358337],"iteration":882,"passed_time":0.7478065346,"remaining_time":0.09908648306},
{"learn":[3.210850401],"iteration":883,"passed_time":0.7484163218,"remaining_time":0.09820847662},
{"learn":[3.207810328],"iteration":884,"passed_time":0.7491432587,"remaining_time":0.09734629916},
{"learn":[3.204935073],"iteration":885,"passed_time":0.7502237609,"remaining_time":0.09652991957},
{"learn":[3.20280198],"iteration":886,"passed_time":0.7508555171,"remaining_time":0.09565577614},
{"learn":[3.200663495],"iteration":887,"passed_time":0.7515628233,"remaining_time":0.09479170744},
{"learn":[3.197301669],"iteration":888,"passed_time":0.7521840747,"remaining_time":0.09391724667},
{"learn":[3.195666943],"iteration":889,"passed_time":0.7527669424,"remaining_time":0.09303861086},
{"learn":[3.193886506],"iteration":890,"passed_time":0.7533693602,"remaining_time":0.09216303059},
{"learn":[3.190601248],"iteration":891,"passed_time":0.75395237,"remaining_time":0.09128571296},
{"learn":[3.188983797],"iteration":892,"passed_time":0.7545441131,"remaining_time":0.09041010089},
{"learn":[3.187365749],"iteration":893,"passed_time":0.7551254304,"remaining_time":0.08953388772},
{"learn":[3.186160771],"iteration":894,"passed_time":0.7557026388,"remaining_time":0.08865785147},
{"learn":[3.185358981],"iteration":895,"passed_time":0.7563247192,"remaining_time":0.08778769062},
{"learn":[3.183832164],"iteration":896,"passed_time":0.7570838499,"remaining_time":0.08693382},
{"learn":[3.183106966],"iteration":897,"passed_time":0.7576879022,"remaining_time":0.08606254568},
{"learn":[3.182838152],"iteration":898,"passed_time":0.7583239498,"remaining_time":0.08519546043},
{"learn":[3.180835453],"iteration":899,"passed_time":0.7589468794,"remaining_time":0.08432743105},
{"learn":[3.179957348],"iteration":900,"passed_time":0.7595572695,"remaining_time":0.0834585679},
{"learn":[3.179752966],"iteration":901,"passed_time":0.7601692176,"remaining_time":0.08259044715},
{"learn":[3.178851983],"iteration":902,"passed_time":0.7607697116,"remaining_time":0.08172166338},
{"learn":[3.176748586],"iteration":903,"passed_time":0.7613771699,"remaining_time":0.08085421273},
{"learn":[3.172960988],"iteration":904,"passed_time":0.7619657651,"remaining_time":0.07998535656},
{"learn":[3.172794225],"iteration":905,"passed_time":0.7625578554,"remaining_time":0.07911748169},
{"learn":[3.169996507],"iteration":906,"passed_time":0.7631768888,"remaining_time":0.07825297758},
{"learn":[3.16813015],"iteration":907,"passed_time":0.7638459753,"remaining_time":0.0773940856},
{"learn":[3.166920871],"iteration":908,"passed_time":0.7646718638,"remaining_time":0.0765513087},
{"learn":[3.16531606],"iteration":909,"passed_time":0.765295065,"remaining_time":0.07568852291},
{"learn":[3.162035247],"iteration":910,"passed_time":0.7658718025,"remaining_time":0.07482172385},
{"learn":[3.16189467],"iteration":911,"passed_time":0.7664389357,"remaining_time":0.07395463415},
{"learn":[3.161008416],"iteration":912,"passed_time":0.7670501666,"remaining_time":0.07309240361},
{"learn":[3.160560787],"iteration":913,"passed_time":0.7676400701,"remaining_time":0.07222871556},
{"learn":[3.160416261],"iteration":914,"passed_time":0.7682214529,"remaining_time":0.07136483443},
{"learn":[3.15844291],"iteration":915,"passed_time":0.768892036,"remaining_time":0.07050975002},
{"learn":[3.155040501],"iteration":916,"passed_time":0.7695218761,"remaining_time":0.06965138028},
{"learn":[3.154937548],"iteration":917,"passed_time":0.7701040089,"remaining_time":0.06878924698},
{"learn":[3.153721161],"iteration":918,"passed_time":0.7707750233,"remaining_time":0.067935557},
{"learn":[3.153170511],"iteration":919,"passed_time":0.7714812381,"remaining_time":0.06708532505},
{"learn":[3.153113601],"iteration":920,"passed_time":0.7720718268,"remaining_time":0.06622548786},
{"learn":[3.150607379],"iteration":921,"passed_time":0.7726669969,"remaining_time":0.0653666223},
{"learn":[3.148408359],"iteration":922,"passed_time":0.7732610665,"remaining_time":0.06450823632},
{"learn":[3.147495728],"iteration":923,"passed_time":0.7738670601,"remaining_time":0.06365140321},
{"learn":[3.146946235],"iteration":924,"passed_time":0.77452103,"remaining_time":0.06279900243},
{"learn":[3.14472738],"iteration":925,"passed_time":0.77514306,"remaining_time":0.0619444778},
{"learn":[3.144469477],"iteration":926,"passed_time":0.7757489409,"remaining_time":0.06108918305},
{"learn":[3.142975516],"iteration":927,"passed_time":0.7763584919,"remaining_time":0.06023471058},
{"learn":[3.14079113],"iteration":928,"passed_time":0.7770140946,"remaining_time":0.05938428495},
{"learn":[3.138173032],"iteration":929,"passed_time":0.7777007821,"remaining_time":0.05853661801},
{"learn":[3.136352813],"iteration":930,"passed_time":0.778324466,"remaining_time":0.05768462745},
{"learn":[3.133735004],"iteration":931,"passed_time":0.7791450029,"remaining_time":0.05684748948},
{"learn":[3.1319496],"iteration":932,"passed_time":0.7799724385,"remaining_time":0.0560108825},
{"learn":[3.129865343],"iteration":933,"passed_time":0.7806006356,"remaining_time":0.05516021622},
{"learn":[3.129830206],"iteration":934,"passed_time":0.7810584436,"remaining_time":0.05429818057},
{"learn":[3.126676562],"iteration":935,"passed_time":0.7816606595,"remaining_time":0.0534468827},
{"learn":[3.12645665],"iteration":936,"passed_time":0.7822288454,"remaining_time":0.05259382845},
{"learn":[3.126378007],"iteration":937,"passed_time":0.782806322,"remaining_time":0.05174199569},
{"learn":[3.124621914],"iteration":938,"passed_time":0.7833920568,"remaining_time":0.05089128377},
{"learn":[3.123379018],"iteration":939,"passed_time":0.7839844531,"remaining_time":0.05004156084},
{"learn":[3.123332451],"iteration":940,"passed_time":0.7845438856,"remaining_time":0.04919031801},
{"learn":[3.122432444],"iteration":941,"passed_time":0.7852881024,"remaining_time":0.04835107212},
{"learn":[3.121889006],"iteration":942,"passed_time":0.7859843118,"remaining_time":0.04750912595},
{"learn":[3.121070914],"iteration":943,"passed_time":0.7865657939,"remaining_time":0.04666068269},
{"learn":[3.118444705],"iteration":944,"passed_time":0.7871777042,"remaining_time":0.04581457537},
{"learn":[3.116820458],"iteration":945,"passed_time":0.787782313,"remaining_time":0.04496854641},
{"learn":[3.114971041],"iteration":946,"passed_time":0.7883763758,"remaining_time":0.04412243708},
{"learn":[3.114685138],"iteration":947,"passed_time":0.789069946,"remaining_time":0.04328231771},
{"learn":[3.113399363],"iteration":948,"passed_time":0.78968951,"remaining_time":0.04243853004},
{"learn":[3.110575399],"iteration":949,"passed_time":0.7903517003,"remaining_time":0.04159745791},
{"learn":[3.110466553],"iteration":950,"passed_time":0.7909294795,"remaining_time":0.04075241272},
{"learn":[3.108691641],"iteration":951,"passed_time":0.7915422684,"remaining_time":0.03990969421},
{"learn":[3.107898017],"iteration":952,"passed_time":0.7922211727,"remaining_time":0.03907071891},
{"learn":[3.105551729],"iteration":953,"passed_time":0.7929012096,"remaining_time":0.0382321338},
{"learn":[3.104824945],"iteration":954,"passed_time":0.7936207265,"remaining_time":0.03739574104},
{"learn":[3.103186704],"iteration":955,"passed_time":0.7944755105,"remaining_time":0.03656581847},
{"learn":[3.102330655],"iteration":956,"passed_time":0.7951461019,"remaining_time":0.0357275678},
{"learn":[3.102291298],"iteration":957,"passed_time":0.7957220012,"remaining_time":0.03488551571},
{"learn":[3.100363529],"iteration":958,"passed_time":0.7963224481,"remaining_time":0.03404506817},
{"learn":[3.097871596],"iteration":959,"passed_time":0.7969165757,"remaining_time":0.03320485732},
{"learn":[3.097372213],"iteration":960,"passed_time":0.7975156757,"remaining_time":0.03236536041},
{"learn":[3.095981813],"iteration":961,"passed_time":0.798095398,"remaining_time":0.03152559784},
{"learn":[3.095347452],"iteration":962,"passed_time":0.7986880063,"remaining_time":0.03068687044},
{"learn":[3.094728409],"iteration":963,"passed_time":0.7995132179,"remaining_time":0.02985734009},
{"learn":[3.094118537],"iteration":964,"passed_time":0.8002030281,"remaining_time":0.02902290776},
{"learn":[3.093793695],"iteration":965,"passed_time":0.8008059874,"remaining_time":0.02818571798},
{"learn":[3.092581602],"iteration":966,"passed_time":0.8013970957,"remaining_time":0.02734860823},
{"learn":[3.091694202],"iteration":967,"passed_time":0.8019994058,"remaining_time":0.02651237705},
{"learn":[3.090298312],"iteration":968,"passed_time":0.8025851053,"remaining_time":0.02567609728},
{"learn":[3.090020107],"iteration":969,"passed_time":0.8031712201,"remaining_time":0.02484034701},
{"learn":[3.088949869],"iteration":970,"passed_time":0.8038275972,"remaining_time":0.02400720939},
{"learn":[3.086700204],"iteration":971,"passed_time":0.8044118505,"remaining_time":0.02317235783},
{"learn":[3.086584317],"iteration":972,"passed_time":0.8049860749,"remaining_time":0.02233774309},
{"learn":[3.084850742],"iteration":973,"passed_time":0.8056650541,"remaining_time":0.02150645935},
{"learn":[3.084239948],"iteration":974,"passed_time":0.8063071108,"remaining_time":0.0206745413},
{"learn":[3.082561673],"iteration":975,"passed_time":0.8070150493,"remaining_time":0.01984463236},
{"learn":[3.07991814],"iteration":976,"passed_time":0.8076408115,"remaining_time":0.01901303855},
{"learn":[3.079350277],"iteration":977,"passed_time":0.8083152622,"remaining_time":0.01818296091},
{"learn":[3.077637462],"iteration":978,"passed_time":0.8090386594,"remaining_time":0.01735425112},
{"learn":[3.076733301],"iteration":979,"passed_time":0.8096943815,"remaining_time":0.01652437513},
{"learn":[3.07594065],"iteration":980,"passed_time":0.8103196241,"remaining_time":0.01569426387},
{"learn":[3.072594655],"iteration":981,"passed_time":0.8109323003,"remaining_time":0.01486433952},
{"learn":[3.071977674],"iteration":982,"passed_time":0.8115100224,"remaining_time":0.01403425268},
{"learn":[3.069532634],"iteration":983,"passed_time":0.812118826,"remaining_time":0.01320518416},
{"learn":[3.068870784],"iteration":984,"passed_time":0.8126939937,"remaining_time":0.01237605067},
{"learn":[3.068801463],"iteration":985,"passed_time":0.8134050599,"remaining_time":0.01154936191},
{"learn":[3.067433249],"iteration":986,"passed_time":0.8142031007,"remaining_time":0.010724053},
{"learn":[3.065611456],"iteration":987,"passed_time":0.8148292472,"remaining_time":0.009896711504},
{"learn":[3.063039162],"iteration":988,"passed_time":0.8154229173,"remaining_time":0.009069415663},
{"learn":[3.06177873],"iteration":989,"passed_time":0.8160060558,"remaining_time":0.008242485412},
{"learn":[3.061689148],"iteration":990,"passed_time":0.8165875446,"remaining_time":0.007416032191},
{"learn":[3.058984039],"iteration":991,"passed_time":0.8172435442,"remaining_time":0.006590673743},
{"learn":[3.057492984],"iteration":992,"passed_time":0.8178592371,"remaining_time":0.005765372266},
{"learn":[3.057290731],"iteration":993,"passed_time":0.8184361394,"remaining_time":0.004940258387},
{"learn":[3.056068348],"iteration":994,"passed_time":0.8190105581,"remaining_time":0.004115630945},
{"learn":[3.054987307],"iteration":995,"passed_time":0.8196013074,"remaining_time":0.003291571515},
{"learn":[3.054200234],"iteration":996,"passed_time":0.8201876147,"remaining_time":0.002467966744},
{"learn":[3.052732869],"iteration":997,"passed_time":0.8208490803,"remaining_time":0.001644988137},
{"learn":[3.051787862],"iteration":998,"passed_time":0.8214388248,"remaining_time":0.0008222610859},
{"learn":[3.051366222],"iteration":999,"passed_time":0.8220259217,"remaining_time":0}
]}